Workbook
Name DvdEnd: Control!$B$6
Name DvdField: Control!$B$4
Name DvdStart: Control!$B$5
Name TkrSuffix: Control!$B$3

Sheet README
A1: README — Dividend history (Bloomberg BDS DVD_HIST_ALL)
A2: For human readers and AI models: read this sheet before using the data.
A4: Key | B4: Value
A5: content | B5: Full dividend/corporate-action history per security from Bloomberg DVD_HIST_ALL, 31 securities (27 stocks + SPY, QQQ, XLK, SMH).
A6: bloomberg_formula | B6: =_xll.BDS(security,"DVD_HIST_ALL","DVD_START_DT=20100101","DVD_END_DT=20261231") — dates on Control!B5:B6 -> #NAME?
A7: columns | B7: Declared Date | Ex-Date | Record Date | Payable Date | Dividend Amount | Dividend Frequency | Dividend Type
A8: dividend_announcement_date
A9: IMPORTANT_dividend_type | B9: DVD_HIST_ALL includes ALL dividend-type corporate actions, not only cash dividends. Rows can include stock splits, spin-offs, special cash, return of capital, etc. ALWAYS filter on the 'Dividend Type' column before summing or computing yield. For stock splits the 'Dividend Amount' is a split ratio, not a cash amount.
A10: ETF_distributions | B10: SPY/QQQ/XLK/SMH rows are fund distributions (may include income and capital-gain distributions, labelled by Dividend Type).
A11: amount_basis | B11: Per-share amount as declared at the time; treat as NOT back-adjusted for later splits unless verified on the terminal. Check before building a continuous per-share dividend series across splits (e.g. NVDA, AAPL, AVGO, GOOGL).
A12: non_payers | B12: Expected no regular cash dividends over the window: AMZN, TSLA, PLTR, MSTR, COIN, HOOD, SHOP, SMCI, NFLX, AMD, ADBE, NOW (flagged on Control col E). Their blocks may be EMPTY (#N/A-type result) or show only non-cash rows such as stock splits. An empty block is expected, NOT a failed pull.
A13: late_initiators | B13: META and GOOGL initiated dividends in 2024, CRM in 2024 — history starts there.
A14: row_order | B14: As returned by Bloomberg (not re-sorted).
A15: currency | B15: Amount currency as returned by Bloomberg per row; TSM is the NYSE ADR (check USD vs TWD and ADR ratio).
A16: layout | B16: Data sheet: row 1 ticker, row 2 Bloomberg security, row 3 payer flag, row 4 headers, data from row 5; 7 columns + 1 spacer per security. Rows NOT aligned across securities.
A17: source | B17: Bloomberg BDS via Excel add-in

Sheet Control
A1: Dividend History Pull — Control Panel
A2: Yellow cells are inputs (blue text).
A3: Ticker suffix | B3: US Equity | C3: Leading space.
A4: BDS field | B4: DVD_HIST_ALL
A5: Override: start | B5: DVD_START_DT=20100101 | C5: Keep the 'DVD_START_DT=' prefix; change the date only.
A6: Override: end | B6: DVD_END_DT=20261231 | C6: Keep the 'DVD_END_DT=' prefix.
A9: Security list
A10: # | B10: Ticker | C10: Bloomberg security | D10: Block col | E10: Regular cash dividend payer?
A11: 1 | B11: SPY | C11: =B11&TkrSuffix -> SPY US Equity | D11: A | E11: YES - ETF distributions
A12: 2 | B12: QQQ | C12: =B12&TkrSuffix -> QQQ US Equity | D12: I | E12: YES - ETF distributions
A13: 3 | B13: XLK | C13: =B13&TkrSuffix -> XLK US Equity | D13: Q | E13: YES - ETF distributions
A14: 4 | B14: SMH | C14: =B14&TkrSuffix -> SMH US Equity | D14: Y | E14: YES - ETF distributions
A15: 5 | B15: AAPL | C15: =B15&TkrSuffix -> AAPL US Equity | D15: AG | E15: YES
A16: 6 | B16: AMZN | C16: =B16&TkrSuffix -> AMZN US Equity | D16: AO | E16: NO - expected empty / non-cash rows only
A17: 7 | B17: GOOGL | C17: =B17&TkrSuffix -> GOOGL US Equity | D17: AW | E17: YES
A18: 8 | B18: META | C18: =B18&TkrSuffix -> META US Equity | D18: BE | E18: YES
A19: 9 | B19: MSFT | C19: =B19&TkrSuffix -> MSFT US Equity | D19: BM | E19: YES
A20: 10 | B20: NFLX | C20: =B20&TkrSuffix -> NFLX US Equity | D20: BU | E20: NO - expected empty / non-cash rows only
A21: 11 | B21: NVDA | C21: =B21&TkrSuffix -> NVDA US Equity | D21: CC | E21: YES
A22: 12 | B22: PLTR | C22: =B22&TkrSuffix -> PLTR US Equity | D22: CK | E22: NO - expected empty / non-cash rows only
... A41: 31 | B41: XOM | C41: =B41&TkrSuffix -> XOM US Equity | D41: IG | E41: YES

Sheet Dividend_Data
A1: =Control!$B$11 -> SPY | I1: =Control!$B$12 -> QQQ | Q1: =Control!$B$13 -> XLK | Y1: =Control!$B$14 -> SMH | AG1: =Control!$B$15 -> AAPL | AO1: =Control!$B$16 -> AMZN | AW1: =Control!$B$17 -> GOOGL | BE1: =Control!$B$18 -> META | BM1: =Control!$B$19 -> MSFT | BU1: =Control!$B$20 -> NFLX | CC1: =Control!$B$21 -> NVDA | CK1: =Control!$B$22 -> PLTR | CS1: =Control!$B$23 -> TSLA | DA1: =Control!$B$24 -> TSM | DI1: =Control!$B$25 -> AVGO | DQ1: =Control!$B$26 -> AMD | DY1: =Control!$B$27 -> MU | EG1: =Control!$B$28 -> MSTR | EO1: =Control!$B$29 -> COIN | EW1: =Control!$B$30 -> HOOD | FE1: =Control!$B$31 -> SHOP | FM1: =Control!$B$32 -> SMCI | FU1: =Control!$B$33 -> ORCL | GC1: =Control!$B$34 -> CRM | GK1: =Control!$B$35 -> ADBE | GS1: =Control!$B$36 -> NOW | HA1: =Control!$B$37 -> LLY | HI1: =Control!$B$38 -> UNH | HQ1: =Control!$B$39 -> JPM | HY1: =Control!$B$40 -> COST | IG1: =Control!$B$41 -> XOM
A2: =Control!$C$11 -> SPY US Equity | I2: =Control!$C$12 -> QQQ US Equity | Q2: =Control!$C$13 -> XLK US Equity | Y2: =Control!$C$14 -> SMH US Equity | AG2: =Control!$C$15 -> AAPL US Equity | AO2: =Control!$C$16 -> AMZN US Equity | AW2: =Control!$C$17 -> GOOGL US Equity | BE2: =Control!$C$18 -> META US Equity | BM2: =Control!$C$19 -> MSFT US Equity | BU2: =Control!$C$20 -> NFLX US Equity | CC2: =Control!$C$21 -> NVDA US Equity | CK2: =Control!$C$22 -> PLTR US Equity | CS2: =Control!$C$23 -> TSLA US Equity | DA2: =Control!$C$24 -> TSM US Equity | DI2: =Control!$C$25 -> AVGO US Equity | DQ2: =Control!$C$26 -> AMD US Equity | DY2: =Control!$C$27 -> MU US Equity | EG2: =Control!$C$28 -> MSTR US Equity | EO2: =Control!$C$29 -> COIN US Equity | EW2: =Control!$C$30 -> HOOD US Equity | FE2: =Control!$C$31 -> SHOP US Equity | FM2: =Control!$C$32 -> SMCI US Equity | FU2: =Control!$C$33 -> ORCL US Equity | GC2: =Control!$C$34 -> CRM US Equity | GK2: =Control!$C$35 -> ADBE US Equity | GS2: =Control!$C$36 -> NOW US Equity | HA2: =Control!$C$37 -> LLY US Equity | HI2: =Control!$C$38 -> UNH US Equity | HQ2: =Control!$C$39 -> JPM US Equity | HY2: =Control!$C$40 -> COST US Equity | IG2: =Control!$C$41 -> XOM US Equity
A3: ="Cash dividend payer: "&Control!$E$11 -> Cash dividend payer: YES - ETF distributions | I3: ="Cash dividend payer: "&Control!$E$12 -> Cash dividend payer: YES - ETF distributions | Q3: ="Cash dividend payer: "&Control!$E$13 -> Cash dividend payer: YES - ETF distributions | Y3: ="Cash dividend payer: "&Control!$E$14 -> Cash dividend payer: YES - ETF distributions | AG3: ="Cash dividend payer: "&Control!$E$15 -> Cash dividend payer: YES | AO3: ="Cash dividend payer: "&Control!$E$16 -> Cash dividend payer: NO - expected empty / non-cash rows only | AW3: ="Cash dividend payer: "&Control!$E$17 -> Cash dividend payer: YES | BE3: ="Cash dividend payer: "&Control!$E$18 -> Cash dividend payer: YES | BM3: ="Cash dividend payer: "&Control!$E$19 -> Cash dividend payer: YES | BU3: ="Cash dividend payer: "&Control!$E$20 -> Cash dividend payer: NO - expected empty / non-cash rows only | CC3: ="Cash dividend payer: "&Control!$E$21 -> Cash dividend payer: YES | CK3: ="Cash dividend payer: "&Control!$E$22 -> Cash dividend payer: NO - expected empty / non-cash rows only | CS3: ="Cash dividend payer: "&Control!$E$23 -> Cash dividend payer: NO - expected empty / non-cash rows only | DA3: ="Cash dividend payer: "&Control!$E$24 -> Cash dividend payer: YES | DI3: ="Cash dividend payer: "&Control!$E$25 -> Cash dividend payer: YES | DQ3: ="Cash dividend payer: "&Control!$E$26 -> Cash dividend payer: NO - expected empty / non-cash rows only | DY3: ="Cash dividend payer: "&Control!$E$27 -> Cash dividend payer: YES | EG3: ="Cash dividend payer: "&Control!$E$28 -> Cash dividend payer: NO - expected empty / non-cash rows only | EO3: ="Cash dividend payer: "&Control!$E$29 -> Cash dividend payer: NO - expected empty / non-cash rows only | EW3: ="Cash dividend payer: "&Control!$E$30 -> Cash dividend payer: NO - expected empty / non-cash rows only | FE3: ="Cash dividend payer: "&Control!$E$31 -> Cash dividend payer: NO - expected empty / non-cash rows only | FM3: ="Cash dividend payer: "&Control!$E$32 -> Cash dividend payer: NO - expected empty / non-cash rows only | FU3: ="Cash dividend payer: "&Control!$E$33 -> Cash dividend payer: YES | GC3: ="Cash dividend payer: "&Control!$E$34 -> Cash dividend payer: YES | GK3: ="Cash dividend payer: "&Control!$E$35 -> Cash dividend payer: NO - expected empty / non-cash rows only | GS3: ="Cash dividend payer: "&Control!$E$36 -> Cash dividend payer: NO - expected empty / non-cash rows only | HA3: ="Cash dividend payer: "&Control!$E$37 -> Cash dividend payer: YES | HI3: ="Cash dividend payer: "&Control!$E$38 -> Cash dividend payer: YES | HQ3: ="Cash dividend payer: "&Control!$E$39 -> Cash dividend payer: YES | HY3: ="Cash dividend payer: "&Control!$E$40 -> Cash dividend payer: YES | IG3: ="Cash dividend payer: "&Control!$E$41 -> Cash dividend payer: YES
A4: Declared Date | B4: Ex-Date | C4: Record Date | D4: Payable Date | E4: Dividend Amount | F4: Dividend Frequency | G4: Dividend Type | I4: Declared Date | J4: Ex-Date | K4: Record Date | L4: Payable Date | M4: Dividend Amount | N4: Dividend Frequency | O4: Dividend Type | Q4: Declared Date | R4: Ex-Date | S4: Record Date | T4: Payable Date | U4: Dividend Amount | V4: Dividend Frequency | W4: Dividend Type | Y4: Declared Date | Z4: Ex-Date | AA4: Record Date | AB4: Payable Date | AC4: Dividend Amount | AD4: Dividend Frequency | AE4: Dividend Type | AG4: Declared Date | AH4: Ex-Date | AI4: Record Date | AJ4: Payable Date | AK4: Dividend Amount | AL4: Dividend Frequency | AM4: Dividend Type | AO4: Declared Date | AP4: Ex-Date | AQ4: Record Date | AR4: Payable Date | AS4: Dividend Amount | AT4: Dividend Frequency | AU4: Dividend Type | AW4: Declared Date | AX4: Ex-Date | AY4: Record Date | AZ4: Payable Date | BA4: Dividend Amount | BB4: Dividend Frequency | BC4: Dividend Type | BE4: Declared Date | BF4: Ex-Date | BG4: Record Date | BH4: Payable Date | BI4: Dividend Amount | BJ4: Dividend Frequency | BK4: Dividend Type | BM4: Declared Date | BN4: Ex-Date | BO4: Record Date | BP4: Payable Date | BQ4: Dividend Amount | BR4: Dividend Frequency | BS4: Dividend Type | BU4: Declared Date | BV4: Ex-Date | BW4: Record Date | BX4: Payable Date | BY4: Dividend Amount | BZ4: Dividend Frequency | CA4: Dividend Type | CC4: Declared Date | CD4: Ex-Date | CE4: Record Date | CF4: Payable Date | CG4: Dividend Amount | CH4: Dividend Frequency | CI4: Dividend Type | CK4: Declared Date | CL4: Ex-Date | CM4: Record Date | CN4: Payable Date | CO4: Dividend Amount | CP4: Dividend Frequency | CQ4: Dividend Type | CS4: Declared Date | CT4: Ex-Date | CU4: Record Date | CV4: Payable Date | CW4: Dividend Amount | CX4: Dividend Frequency | CY4: Dividend Type | DA4: Declared Date | DB4: Ex-Date | DC4: Record Date | DD4: Payable Date | DE4: Dividend Amount | DF4: Dividend Frequency | DG4: Dividend Type | DI4: Declared Date | DJ4: Ex-Date | DK4: Record Date | DL4: Payable Date | DM4: Dividend Amount | DN4: Dividend Frequency | DO4: Dividend Type | DQ4: Declared Date | DR4: Ex-Date | DS4: Record Date | DT4: Payable Date | DU4: Dividend Amount | DV4: Dividend Frequency | DW4: Dividend Type | DY4: Declared Date | DZ4: Ex-Date | EA4: Record Date | EB4: Payable Date | EC4: Dividend Amount | ED4: Dividend Frequency | EE4: Dividend Type | EG4: Declared Date | EH4: Ex-Date | EI4: Record Date | EJ4: Payable Date | EK4: Dividend Amount | EL4: Dividend Frequency | EM4: Dividend Type | EO4: Declared Date | EP4: Ex-Date | EQ4: Record Date | ER4: Payable Date | ES4: Dividend Amount | ET4: Dividend Frequency | EU4: Dividend Type | EW4: Declared Date | EX4: Ex-Date | EY4: Record Date | EZ4: Payable Date | FA4: Dividend Amount | FB4: Dividend Frequency | FC4: Dividend Type | FE4: Declared Date | FF4: Ex-Date | FG4: Record Date | FH4: Payable Date | FI4: Dividend Amount | FJ4: Dividend Frequency | FK4: Dividend Type | FM4: Declared Date | FN4: Ex-Date | FO4: Record Date | FP4: Payable Date | FQ4: Dividend Amount | FR4: Dividend Frequency | FS4: Dividend Type | FU4: Declared Date | FV4: Ex-Date | FW4: Record Date | FX4: Payable Date | FY4: Dividend Amount | FZ4: Dividend Frequency | GA4: Dividend Type | GC4: Declared Date | GD4: Ex-Date | GE4: Record Date | GF4: Payable Date | GG4: Dividend Amount | GH4: Dividend Frequency | GI4: Dividend Type | GK4: Declared Date | GL4: Ex-Date | GM4: Record Date | GN4: Payable Date | GO4: Dividend Amount | GP4: Dividend Frequency | GQ4: Dividend Type | GS4: Declared Date | GT4: Ex-Date | GU4: Record Date | GV4: Payable Date | GW4: Dividend Amount | GX4: Dividend Frequency | GY4: Dividend Type | HA4: Declared Date | HB4: Ex-Date | HC4: Record Date | HD4: Payable Date | HE4: Dividend Amount | HF4: Dividend Frequency | HG4: Dividend Type | HI4: Declared Date | HJ4: Ex-Date | HK4: Record Date | HL4: Payable Date | HM4: Dividend Amount | HN4: Dividend Frequency | HO4: Dividend Type | HQ4: Declared Date | HR4: Ex-Date | HS4: Record Date | HT4: Payable Date | HU4: Dividend Amount | HV4: Dividend Frequency | HW4: Dividend Type | HY4: Declared Date | HZ4: Ex-Date | IA4: Record Date | IB4: Payable Date | IC4: Dividend Amount | ID4: Dividend Frequency | IE4: Dividend Type | IG4: Declared Date | IH4: Ex-Date | II4: Record Date | IJ4: Payable Date | IK4: Dividend Amount | IL4: Dividend Frequency | IM4: Dividend Type
A5: =_xll.BDS(A$2,DvdField,DvdStart,DvdEnd,"cols=7;rows=67") -> 46282 | B5: 46283 | C5: 46283 | D5: 46325 | E5: 1.888834 | F5: Quarter | G5: Income | I5: =_xll.BDS(I$2,DvdField,DvdStart,DvdEnd,"cols=7;rows=69") -> 46283 | J5: 46286 | K5: 46286 | L5: 46303 | M5: 0.75143 | N5: Quarter | O5: Income | Q5: =_xll.BDS(Q$2,DvdField,DvdStart,DvdEnd,"cols=7;rows=68") -> 46283 | R5: 46286 | S5: 46286 | T5: 46288 | U5: 0.220686 | V5: Quarter | W5: Income | Y5: =_xll.BDS(Y$2,DvdField,DvdStart,DvdEnd,"cols=7;rows=17") -> 46010 | Z5: 46013 | AA5: 46013 | AB5: 46017 | AC5: 1.1047 | AD5: Annual | AE5: Income | AG5: =_xll.BDS(AG$2,DvdField,DvdStart,DvdEnd,"cols=7;rows=59") -> 46233 | AH5: 46244 | AI5: 46244 | AJ5: 46247 | AK5: 0.27 | AL5: Quarter | AM5: Regular Cash | AO5: =_xll.BDS(AO$2,DvdField,DvdStart,DvdEnd,"cols=7;rows=1") -> 44629 | AP5: 44718 | AQ5: 44708 | AR5: 44715 | AS5: 20 | AT5: None | AU5: Stock Split | AW5: =_xll.BDS(AW$2,DvdField,DvdStart,DvdEnd,"cols=7;rows=12") -> 46225 | AX5: 46269 | AY5: 46272 | AZ5: 46279 | BA5: 0.22 | BB5: Quarter | BC5: Regular Cash | BE5: =_xll.BDS(BE$2,DvdField,DvdStart,DvdEnd,"cols=7;rows=12") -> 46275 | BF5: 46286 | BG5: 46286 | BH5: 46293 | BI5: 0.525 | BJ5: Quarter | BK5: Regular Cash | BM5: =_xll.BDS(BM$2,DvdField,DvdStart,DvdEnd,"cols=7;rows=68") -> 46280 | BN5: 46345 | BO5: 46345 | BP5: 46366 | BQ5: 0.98 | BR5: Quarter | BS5: Regular Cash | BU5: =_xll.BDS(BU$2,DvdField,DvdStart,DvdEnd,"cols=7;rows=3") -> 45960 | BV5: 45978 | BW5: 45971 | BX5: 45975 | BY5: 10 | BZ5: None | CA5: Stock Split | CC5: =_xll.BDS(CC$2,DvdField,DvdStart,DvdEnd,"cols=7;rows=58") -> 46260 | CD5: 46275 | CE5: 46275 | CF5: 46296 | CG5: 0.25 | CH5: Quarter | CI5: Regular Cash | CK5: =_xll.BDS(CK$2,DvdField,DvdStart,DvdEnd) -> #N/A Field Not Applicable | CS5: =_xll.BDS(CS$2,DvdField,DvdStart,DvdEnd,"cols=7;rows=2") -> 44778 | CT5: 44798 | CU5: 44790 | CV5: 44797 | CW5: 3 | CX5: None | CY5: Stock Split | DA5: =_xll.BDS(DA$2,DvdField,DvdStart,DvdEnd,"cols=7;rows=40") -> 46245 | DB5: 46366 | DC5: 46366 | DD5: 46394 | DE5: 0.857497 | DF5: Quarter | DG5: Regular Cash | DI5: =_xll.BDS(DI$2,DvdField,DvdStart,DvdEnd,"cols=7;rows=65") -> 46267 | DJ5: 46286 | DK5: 46286 | DL5: 46295 | DM5: 0.65 | DN5: Quarter | DO5: Regular Cash | DQ5: =_xll.BDS(DQ$2,DvdField,DvdStart,DvdEnd) -> #N/A Field Not Applicable | DY5: =_xll.BDS(DY$2,DvdField,DvdStart,DvdEnd,"cols=7;rows=21") -> 46197 | DZ5: 46209 | EA5: 46209 | EB5: 46224 | EC5: 0.15 | ED5: Quarter | EE5: Regular Cash | EG5: =_xll.BDS(EG$2,DvdField,DvdStart,DvdEnd,"cols=7;rows=1") -> 45484 | EH5: 45512 | EI5: 45505 | EJ5: 45511 | EK5: 10 | EL5: None | EM5: Stock Split | EO5: =_xll.BDS(EO$2,DvdField,DvdStart,DvdEnd) -> #N/A Field Not Applicable | EW5: =_xll.BDS(EW$2,DvdField,DvdStart,DvdEnd) -> #N/A Field Not Applicable | FE5: =_xll.BDS(FE$2,DvdField,DvdStart,DvdEnd,"cols=7;rows=1") -> 44662 | FF5: 44741 | FG5: 44734 | FH5: 44740 | FI5: 10 | FJ5: None | FK5: Stock Split | FM5: =_xll.BDS(FM$2,DvdField,DvdStart,DvdEnd,"cols=7;rows=1") -> 45510 | FN5: 45566 | FO5: #N/A N/A | FP5: #N/A N/A | FQ5: 10 | FR5: None | FS5: Stock Split | FU5: =_xll.BDS(FU$2,DvdField,DvdStart,DvdEnd,"cols=7;rows=69") -> 46275 | FV5: 46304 | FW5: 46304 | FX5: 46318 | FY5: 0.5 | FZ5: Quarter | GA5: Regular Cash | GC5: =_xll.BDS(GC$2,DvdField,DvdStart,DvdEnd,"cols=7;rows=12") -> 46268 | GD5: 46282 | GE5: 46282 | GF5: 46303 | GG5: 0.44 | GH5: Quarter | GI5: Regular Cash | GK5: =_xll.BDS(GK$2,DvdField,DvdStart,DvdEnd) -> #N/A Field Not Applicable | GS5: =_xll.BDS(GS$2,DvdField,DvdStart,DvdEnd,"cols=7;rows=1") -> 45959 | GT5: 46009 | GU5: 46007 | GV5: 46008 | GW5: 5 | GX5: None | GY5: Stock Split | HA5: =_xll.BDS(HA$2,DvdField,DvdStart,DvdEnd,"cols=7;rows=68") -> 46195 | HB5: 46248 | HC5: 46248 | HD5: 46275 | HE5: 1.73 | HF5: Quarter | HG5: Regular Cash | HI5: =_xll.BDS(HI$2,DvdField,DvdStart,DvdEnd,"cols=7;rows=67") -> 46246 | HJ5: 46279 | HK5: 46279 | HL5: 46287 | HM5: 2.32 | HN5: Quarter | HO5: Regular Cash | HQ5: =_xll.BDS(HQ$2,DvdField,DvdStart,DvdEnd,"cols=7;rows=68") -> 46280 | HR5: 46301 | HS5: 46301 | HT5: 46326 | HU5: 1.65 | HV5: Quarter | HW5: Regular Cash | HY5: =_xll.BDS(HY$2,DvdField,DvdStart,DvdEnd,"cols=7;rows=72") -> 46211 | HZ5: 46227 | IA5: 46227 | IB5: 46241 | IC5: 1.47 | ID5: Quarter | IE5: Regular Cash | IG5: =_xll.BDS(IG$2,DvdField,DvdStart,DvdEnd,"cols=7;rows=67") -> 46234 | IH5: 46251 | II5: 46251 | IJ5: 46275 | IK5: 1.03 | IL5: Quarter | IM5: Regular Cash
A6: 46190 | B6: 46191 | C6: 46191 | D6: 46234 | E6: 1.903516 | F6: Quarter | G6: Income | I6: 46191 | J6: 46195 | K6: 46195 | L6: 46213 | M6: 0.81349 | N6: Quarter | O6: Income | Q6: 46191 | R6: 46195 | S6: 46195 | T6: 46197 | U6: 0.227918 | V6: Quarter | W6: Income | Y6: 45652 | Z6: 45653 | AA6: 45653 | AB6: 45656 | AC6: -2.4245363e-14 | AD6: Annual | AE6: Omitted | AG6: 46142 | AH6: 46153 | AI6: 46153 | AJ6: 46156 | AK6: 0.27 | AL6: Quarter | AM6: Regular Cash | AW6: 46139 | AX6: 46181 | AY6: 46181 | AZ6: 46188 | BA6: 0.22 | BB6: Quarter | BC6: Regular Cash | BE6: 46170 | BF6: 46188 | BG6: 46188 | BH6: 46198 | BI6: 0.525 | BJ6: Quarter | BK6: Regular Cash | BM6: 46183 | BN6: 46254 | BO6: 46254 | BP6: 46275 | BQ6: 0.91 | BR6: Quarter | BS6: Regular Cash | BU6: 42178 | BV6: 42200 | BW6: 42187 | BX6: 42199 | BY6: 7 | BZ6: None | CA6: Stock Split | CC6: 46162 | CD6: 46177 | CE6: 46177 | CF6: 46199 | CG6: 0.25 | CH6: Quarter | CI6: Regular Cash | CS6: 44054 | CT6: 44074 | CU6: 44064 | CV6: 44071 | CW6: 5 | CX6: None | CY6: Stock Split | DA6: 46154 | DB6: 46281 | DC6: 46281 | DD6: 46303 | DE6: 0.874889 | DF6: Quarter | DG6: Regular Cash | DI6: 46176 | DJ6: 46195 | DK6: 46195 | DL6: 46203 | DM6: 0.65 | DN6: Quarter | DO6: Regular Cash | DY6: 46099 | DZ6: 46111 | EA6: 46111 | EB6: 46127 | EC6: 0.15 | ED6: Quarter | EE6: Regular Cash | FU6: 46183 | FV6: 46213 | FW6: 46213 | FX6: 46227 | FY6: 0.5 | FZ6: Quarter | GA6: Regular Cash | GC6: 46170 | GD6: 46184 | GE6: 46184 | GF6: 46205 | GG6: 0.44 | GH6: Quarter | GI6: Regular Cash | HA6: 46146 | HB6: 46157 | HC6: 46157 | HD6: 46183 | HE6: 1.73 | HF6: Quarter | HG6: Regular Cash | HI6: 46176 | HJ6: 46188 | HK6: 46188 | HL6: 46196 | HM6: 2.32 | HN6: Quarter | HO6: Regular Cash | HQ6: 46160 | HR6: 46209 | HS6: 46209 | HT6: 46234 | HU6: 1.5 | HV6: Quarter | HW6: Regular Cash | HY6: 46127 | HZ6: 46143 | IA6: 46143 | IB6: 46157 | IC6: 1.47 | ID6: Quarter | IE6: Regular Cash | IG6: 46143 | IH6: 46157 | II6: 46157 | IJ6: 46183 | IK6: 1.03 | IL6: Quarter | IM6: Regular Cash
A7: 46100 | B7: 46101 | C7: 46101 | D7: 46142 | E7: 1.796999 | F7: Quarter | G7: Income | I7: 46101 | J7: 46104 | K7: 46104 | L7: 46108 | M7: 0.73282 | N7: Quarter | O7: Income | Q7: 46101 | R7: 46104 | S7: 46104 | T7: 46106 | U7: 0.167505 | V7: Quarter | W7: Income | Y7: 45646 | Z7: 45649 | AA7: 45649 | AB7: 45650 | AC7: 1.0713 | AD7: Annual | AE7: Income | AG7: 46051 | AH7: 46062 | AI7: 46062 | AJ7: 46065 | AK7: 0.26 | AL7: Quarter | AM7: Regular Cash | AW7: 46057 | AX7: 46090 | AY7: 46090 | AZ7: 46097 | BA7: 0.21 | BB7: Quarter | BC7: Regular Cash | BE7: 46065 | BF7: 46097 | BG7: 46097 | BH7: 46107 | BI7: 0.525 | BJ7: Quarter | BK7: Regular Cash | BM7: 46091 | BN7: 46163 | BO7: 46163 | BP7: 46184 | BQ7: 0.91 | BR7: Quarter | BS7: Regular Cash | BU7: 41218 | BV7: 41218 | BW7: 41215 | BX7: #N/A N/A | BY7: 1 | BZ7: None | CA7: Poison Pill Rights | CC7: 46078 | CD7: 46092 | CE7: 46092 | CF7: 46113 | CG7: 0.01 | CH7: Quarter | CI7: Regular Cash | DA7: 46063 | DB7: 46184 | DC7: 46184 | DD7: 46212 | DE7: 0.742067 | DF7: Quarter | DG7: Regular Cash | DI7: 46085 | DJ7: 46104 | DK7: 46104 | DL7: 46112 | DM7: 0.65 | DN7: Quarter | DO7: Regular Cash | DY7: 46008 | DZ7: 46020 | EA7: 46020 | EB7: 46036 | EC7: 0.115 | ED7: Quarter | EE7: Regular Cash | FU7: 46091 | FV7: 46121 | FW7: 46121 | FX7: 46136 | FY7: 0.5 | FZ7: Quarter | GA7: Regular Cash | GC7: 46078 | GD7: 46121 | GE7: 46121 | GF7: 46135 | GG7: 0.44 | GH7: Quarter | GI7: Regular Cash | HA7: 45999 | HB7: 46066 | HC7: 46066 | HD7: 46091 | HE7: 1.73 | HF7: Quarter | HG7: Regular Cash | HI7: 46078 | HJ7: 46090 | HK7: 46090 | HL7: 46098 | HM7: 2.21 | HN7: Quarter | HO7: Regular Cash | HQ7: 46098 | HR7: 46118 | HS7: 46118 | HT7: 46142 | HU7: 1.5 | HV7: Quarter | HW7: Regular Cash | HY7: 46037 | HZ7: 46052 | IA7: 46052 | IB7: 46066 | IC7: 1.3 | ID7: Quarter | IE7: Regular Cash | IG7: 46052 | IH7: 46065 | II7: 46065 | IJ7: 46091 | IK7: 1.03 | IL7: Quarter | IM7: Regular Cash
A8: 46009 | B8: 46010 | C8: 46010 | D8: 46052 | E8: 1.993368 | F8: Quarter | G8: Income | I8: 46010 | J8: 46013 | K8: 46013 | L8: 46022 | M8: 0.79408 | N8: Quarter | O8: Income | Q8: 46010 | R8: 46013 | S8: 46013 | T8: 46015 | U8: 0.218827 | V8: Quarter | W8: Income | Y8: 45286 | Z8: 45287 | AA8: 45288 | AB8: 45289 | AC8: -2.4245363e-14 | AD8: Annual | AE8: Omitted | AG8: 45960 | AH8: 45971 | AI8: 45971 | AJ8: 45974 | AK8: 0.26 | AL8: Quarter | AM8: Regular Cash | AW8: 45964 | AX8: 45999 | AY8: 45999 | AZ8: 46006 | BA8: 0.21 | BB8: Quarter | BC8: Regular Cash | BE8: 45994 | BF8: 46006 | BG8: 46006 | BH8: 46014 | BI8: 0.525 | BJ8: Quarter | BK8: Regular Cash | BM8: 45993 | BN8: 46072 | BO8: 46072 | BP8: 46093 | BQ8: 0.91 | BR8: Quarter | BS8: Regular Cash | CC8: 45980 | CD8: 45995 | CE8: 45995 | CF8: 46017 | CG8: 0.01 | CH8: Quarter | CI8: Regular Cash | DA8: 45973 | DB8: 46098 | DC8: 46098 | DD8: 46121 | DE8: 0.741788 | DF8: Quarter | DG8: Regular Cash | DI8: 46002 | DJ8: 46013 | DK8: 46013 | DL8: 46022 | DM8: 0.65 | DN8: Quarter | DO8: Regular Cash | DY8: 45923 | DZ8: 45933 | EA8: 45933 | EB8: 45951 | EC8: 0.115 | ED8: Quarter | EE8: Regular Cash | FU8: 46001 | FV8: 46031 | FW8: 46031 | FX8: 46045 | FY8: 0.5 | FZ8: Quarter | GA8: Regular Cash | GC8: 45995 | GD8: 46009 | GE8: 46009 | GF8: 46030 | GG8: 0.416 | GH8: Quarter | GI8: Regular Cash | HA8: 45957 | HB8: 45975 | HC8: 45975 | HD8: 46001 | HE8: 1.5 | HF8: Quarter | HG8: Regular Cash | HI8: 45968 | HJ8: 45999 | HK8: 45999 | HL8: 46007 | HM8: 2.21 | HN8: Quarter | HO8: Regular Cash | HQ8: 46000 | HR8: 46028 | HS8: 46028 | HT8: 46053 | HU8: 1.5 | HV8: Quarter | HW8: Regular Cash | HY8: 45945 | HZ8: 45961 | IA8: 45961 | IB8: 45975 | IC8: 1.3 | ID8: Quarter | IE8: Regular Cash | IG8: 45961 | IH8: 45975 | II8: 45975 | IJ8: 46001 | IK8: 1.03 | IL8: Quarter | IM8: Regular Cash
A9: 45918 | B9: 45919 | C9: 45919 | D9: 45961 | E9: 1.831114 | F9: Quarter | G9: Income | I9: 45919 | J9: 45922 | K9: 45922 | L9: 45961 | M9: 0.69395 | N9: Quarter | O9: Income | Q9: 45981 | R9: 45996 | S9: 45993 | T9: 45995 | U9: 2 | V9: None | W9: Stock Split | Y9: 45275 | Z9: 45278 | AA9: 45279 | AB9: 45282 | AC9: 1.0427 | AD9: Annual | AE9: Income | AG9: 45869 | AH9: 45880 | AI9: 45880 | AJ9: 45883 | AK9: 0.26 | AL9: Quarter | AM9: Regular Cash | AW9: 45861 | AX9: 45908 | AY9: 45908 | AZ9: 45915 | BA9: 0.21 | BB9: Quarter | BC9: Regular Cash | BE9: 45911 | BF9: 45922 | BG9: 45922 | BH9: 45929 | BI9: 0.525 | BJ9: Quarter | BK9: Regular Cash | BM9: 45915 | BN9: 45981 | BO9: 45981 | BP9: 46002 | BQ9: 0.91 | BR9: Quarter | BS9: Regular Cash | CC9: 45896 | CD9: 45911 | CE9: 45911 | CF9: 45932 | CG9: 0.01 | CH9: Quarter | CI9: Regular Cash | DA9: 45881 | DB9: 46002 | DC9: 46002 | DD9: 46030 | DE9: 0.628382 | DF9: Quarter | DG9: Regular Cash | DI9: 45904 | DJ9: 45922 | DK9: 45922 | DL9: 45930 | DM9: 0.59 | DN9: Quarter | DO9: Regular Cash | DY9: 45833 | DZ9: 45845 | EA9: 45845 | EB9: 45860 | EC9: 0.115 | ED9: Quarter | EE9: Regular Cash | FU9: 45909 | FV9: 45939 | FW9: 45939 | FX9: 45953 | FY9: 0.5 | FZ9: Quarter | GA9: Regular Cash | GC9: 45904 | GD9: 45917 | GE9: 45917 | GF9: 45939 | GG9: 0.416 | GH9: Quarter | GI9: Regular Cash | HA9: 45831 | HB9: 45884 | HC9: 45884 | HD9: 45910 | HE9: 1.5 | HF9: Quarter | HG9: Regular Cash | HI9: 45882 | HJ9: 45915 | HK9: 45915 | HL9: 45923 | HM9: 2.21 | HN9: Quarter | HO9: Regular Cash | HQ9: 45916 | HR9: 45936 | HS9: 45936 | HT9: 45961 | HU9: 1.5 | HV9: Quarter | HW9: Regular Cash | HY9: 45854 | HZ9: 45870 | IA9: 45870 | IB9: 45884 | IC9: 1.3 | ID9: Quarter | IE9: Regular Cash | IG9: 45870 | IH9: 45884 | II9: 45884 | IJ9: 45910 | IK9: 0.99 | IL9: Quarter | IM9: Regular Cash
A10: 45826 | B10: 45828 | C10: 45828 | D10: 45869 | E10: 1.761117 | F10: Quarter | G10: Income | I10: 45828 | J10: 45831 | K10: 45831 | L10: 45869 | M10: 0.59111 | N10: Quarter | O10: Income | Q10: 45919 | R10: 45922 | S10: 45922 | T10: 45924 | U10: 0.178934 | V10: Quarter | W10: Income | Y10: 45027 | Z10: 45051 | AA10: 45049 | AB10: 45050 | AC10: 2 | AD10: None | AE10: Stock Split | AG10: 45778 | AH10: 45789 | AI10: 45789 | AJ10: 45792 | AK10: 0.26 | AL10: Quarter | AM10: Regular Cash | AW10: 45771 | AX10: 45817 | AY10: 45817 | AZ10: 45824 | BA10: 0.21 | BB10: Quarter | BC10: Regular Cash | BE10: 45806 | BF10: 45824 | BG10: 45824 | BH10: 45834 | BI10: 0.525 | BJ10: Quarter | BK10: Regular Cash | BM10: 45818 | BN10: 45890 | BO10: 45890 | BP10: 45911 | BQ10: 0.83 | BR10: Quarter | BS10: Regular Cash | CC10: 45805 | CD10: 45819 | CE10: 45819 | CF10: 45841 | CG10: 0.01 | CH10: Quarter | CI10: Regular Cash | DA10: 45790 | DB10: 45916 | DC10: 45916 | DD10: 45939 | DE10: 0.649352 | DF10: Quarter | DG10: Regular Cash | DI10: 45813 | DJ10: 45828 | DK10: 45828 | DL10: 45838 | DM10: 0.59 | DN10: Quarter | DO10: Regular Cash | DY10: 45736 | DZ10: 45747 | EA10: 45747 | EB10: 45762 | EC10: 0.115 | ED10: Quarter | EE10: Regular Cash | FU10: 45819 | FV10: 45848 | FW10: 45848 | FX10: 45862 | FY10: 0.5 | FZ10: Quarter | GA10: Regular Cash | GC10: 45813 | GD10: 45826 | GE10: 45826 | GF10: 45848 | GG10: 0.416 | GH10: Quarter | GI10: Regular Cash | HA10: 45782 | HB10: 45793 | HC10: 45793 | HD10: 45818 | HE10: 1.5 | HF10: Quarter | HG10: Regular Cash | HI10: 45812 | HJ10: 45824 | HK10: 45824 | HL10: 45832 | HM10: 2.21 | HN10: Quarter | HO10: Regular Cash | HQ10: 45796 | HR10: 45841 | HS10: 45841 | HT10: 45869 | HU10: 1.4 | HV10: Quarter | HW10: Regular Cash | HY10: 45763 | HZ10: 45779 | IA10: 45779 | IB10: 45793 | IC10: 1.3 | ID10: Quarter | IE10: Regular Cash | IG10: 45779 | IH10: 45792 | II10: 45792 | IJ10: 45818 | IK10: 0.99 | IL10: Quarter | IM10: Regular Cash
A11: 45736 | B11: 45737 | C11: 45737 | D11: 45777 | E11: 1.695528 | F11: Quarter | G11: Income | I11: 45737 | J11: 45740 | K11: 45740 | L11: 45777 | M11: 0.71571 | N11: Quarter | O11: Income | Q11: 45828 | R11: 45831 | S11: 45831 | T11: 45833 | U11: 0.198754 | V11: Quarter | W11: Income | Y11: 44911 | Z11: 44914 | AA11: 44915 | AB11: 44918 | AC11: 1.2005 | AD11: Annual | AE11: Income | AG11: 45687 | AH11: 45698 | AI11: 45698 | AJ11: 45701 | AK11: 0.25 | AL11: Quarter | AM11: Regular Cash | AW11: 45692 | AX11: 45726 | AY11: 45726 | AZ11: 45733 | BA11: 0.2 | BB11: Quarter | BC11: Regular Cash | BE11: 45701 | BF11: 45730 | BG11: 45730 | BH11: 45742 | BI11: 0.525 | BJ11: Quarter | BK11: Regular Cash | BM11: 45727 | BN11: 45792 | BO11: 45792 | BP11: 45820 | BQ11: 0.83 | BR11: Quarter | BS11: Regular Cash | CC11: 45714 | CD11: 45728 | CE11: 45728 | CF11: 45749 | CG11: 0.01 | CH11: Quarter | CI11: Regular Cash | DA11: 45700 | DB11: 45820 | DC11: 45820 | DD11: 45848 | DE11: 0.616441 | DF11: Quarter | DG11: Regular Cash | DI11: 45722 | DJ11: 45736 | DK11: 45736 | DL11: 45747 | DM11: 0.59 | DN11: Quarter | DO11: Regular Cash | DY11: 45644 | DZ11: 45656 | EA11: 45656 | EB11: 45672 | EC11: 0.115 | ED11: Quarter | EE11: Regular Cash | FU11: 45726 | FV11: 45757 | FW11: 45757 | FX11: 45770 | FY11: 0.5 | FZ11: Quarter | GA11: Regular Cash | GC11: 45743 | GD11: 45757 | GE11: 45757 | GF11: 45771 | GG11: 0.416 | GH11: Quarter | GI11: Regular Cash | HA11: 45635 | HB11: 45702 | HC11: 45702 | HD11: 45726 | HE11: 1.5 | HF11: Quarter | HG11: Regular Cash | HI11: 45712 | HJ11: 45726 | HK11: 45726 | HL11: 45734 | HM11: 2.1 | HN11: Quarter | HO11: Regular Cash | HQ11: 45734 | HR11: 45751 | HS11: 45751 | HT11: 45777 | HU11: 1.4 | HV11: Quarter | HW11: Regular Cash | HY11: 45680 | HZ11: 45695 | IA11: 45695 | IB11: 45709 | IC11: 1.16 | ID11: Quarter | IE11: Regular Cash | IG11: 45688 | IH11: 45700 | II11: 45700 | IJ11: 45726 | IK11: 0.99 | IL11: Quarter | IM11: Regular Cash
A12: 45645 | B12: 45646 | C12: 45646 | D12: 45688 | E12: 1.965548 | F12: Quarter | G12: Income | I12: 45646 | J12: 45649 | K12: 45649 | L12: 45657 | M12: 0.83466 | N12: Quarter | O12: Income | Q12: 45737 | R12: 45740 | S12: 45740 | T12: 45742 | U12: 0.187446 | V12: Quarter | W12: Income | Y12: 44547 | Z12: 44550 | AA12: 44551 | AB12: 44557 | AC12: 0.78665 | AD12: Annual | AE12: Income | AG12: 45596 | AH12: 45604 | AI12: 45607 | AJ12: 45610 | AK12: 0.25 | AL12: Quarter | AM12: Regular Cash | AW12: 45595 | AX12: 45635 | AY12: 45635 | AZ12: 45642 | BA12: 0.2 | BB12: Quarter | BC12: Regular Cash | BE12: 45631 | BF12: 45642 | BG12: 45642 | BH12: 45653 | BI12: 0.5 | BJ12: Quarter | BK12: Regular Cash | BM12: 45629 | BN12: 45708 | BO12: 45708 | BP12: 45729 | BQ12: 0.83 | BR12: Quarter | BS12: Regular Cash | CC12: 45616 | CD12: 45631 | CE12: 45631 | CF12: 45653 | CG12: 0.01 | CH12: Quarter | CI12: Regular Cash | DA12: 45608 | DB12: 45734 | DC12: 45734 | DD12: 45757 | DE12: 0.535377 | DF12: Quarter | DG12: Regular Cash | DI12: 45638 | DJ12: 45649 | DK12: 45649 | DL12: 45657 | DM12: 0.59 | DN12: Quarter | DO12: Regular Cash | DY12: 45560 | DZ12: 45572 | EA12: 45572 | EB12: 45588 | EC12: 0.115 | ED12: Quarter | EE12: Regular Cash | FU12: 45635 | FV12: 45667 | FW12: 45666 | FX12: 45680 | FY12: 0.4 | FZ12: Quarter | GA12: Regular Cash | GC12: 45631 | GD12: 45644 | GE12: 45644 | GF12: 45666 | GG12: 0.4 | GH12: Quarter | GI12: Regular Cash | HA12: 45593 | HB12: 45611 | HC12: 45611 | HD12: 45636 | HE12: 1.3 | HF12: Quarter | HG12: Regular Cash | HI12: 45602 | HJ12: 45635 | HK12: 45635 | HL12: 45643 | HM12: 2.1 | HN12: Quarter | HO12: Regular Cash | HQ12: 45635 | HR12: 45663 | HS12: 45663 | HT12: 45688 | HU12: 1.25 | HV12: Quarter | HW12: Regular Cash | HY12: 45581 | HZ12: 45597 | IA12: 45597 | IB12: 45611 | IC12: 1.16 | ID12: Quarter | IE12: Regular Cash | IG12: 45597 | IH12: 45610 | II12: 45610 | IJ12: 45636 | IK12: 0.99 | IL12: Quarter | IM12: Regular Cash
A13: 45554 | B13: 45555 | C13: 45555 | D13: 45596 | E13: 1.745531 | F13: Quarter | G13: Income | I13: 45556 | J13: 45558 | K13: 45558 | L13: 45596 | M13: 0.67686 | N13: Quarter | O13: Income | Q13: 45646 | R13: 45649 | S13: 45649 | T13: 45652 | U13: 0.192979 | V13: Quarter | W13: Income | Y13: 44183 | Z13: 44186 | AA13: 44187 | AB13: 44193 | AC13: 0.7511 | AD13: Annual | AE13: Income | AG13: 45505 | AH13: 45516 | AI13: 45516 | AJ13: 45519 | AK13: 0.25 | AL13: Quarter | AM13: Regular Cash | AW13: 45498 | AX13: 45544 | AY13: 45544 | AZ13: 45551 | BA13: 0.2 | BB13: Quarter | BC13: Regular Cash | BE13: 45540 | BF13: 45551 | BG13: 45551 | BH13: 45561 | BI13: 0.5 | BJ13: Quarter | BK13: Regular Cash | BM13: 45551 | BN13: 45617 | BO13: 45617 | BP13: 45638 | BQ13: 0.83 | BR13: Quarter | BS13: Regular Cash | CC13: 45532 | CD13: 45547 | CE13: 45547 | CF13: 45568 | CG13: 0.01 | CH13: Quarter | CI13: Regular Cash | DA13: 45517 | DB13: 45638 | DC13: 45638 | DD13: 45666 | DE13: 0.480404 | DF13: Quarter | DG13: Regular Cash | DI13: 45540 | DJ13: 45554 | DK13: 45554 | DL13: 45565 | DM13: 0.53 | DN13: Quarter | DO13: Regular Cash | DY13: 45469 | DZ13: 45481 | EA13: 45481 | EB13: 45496 | EC13: 0.115 | ED13: Quarter | EE13: Regular Cash | FU13: 45544 | FV13: 45575 | FW13: 45575 | FX13: 45589 | FY13: 0.4 | FZ13: Quarter | GA13: Regular Cash | GC13: 45540 | GD13: 45553 | GE13: 45553 | GF13: 45573 | GG13: 0.4 | GH13: Quarter | GI13: Regular Cash | HA13: 45467 | HB13: 45519 | HC13: 45519 | HD13: 45545 | HE13: 1.3 | HF13: Quarter | HG13: Regular Cash | HI13: 45511 | HJ13: 45551 | HK13: 45551 | HL13: 45559 | HM13: 2.1 | HN13: Quarter | HO13: Regular Cash | HQ13: 45552 | HR13: 45569 | HS13: 45569 | HT13: 45596 | HU13: 1.25 | HV13: Quarter | HW13: Regular Cash | HY13: 45483 | HZ13: 45499 | IA13: 45499 | IB13: 45513 | IC13: 1.16 | ID13: Quarter | IE13: Regular Cash | IG13: 45506 | IH13: 45519 | II13: 45519 | IJ13: 45545 | IK13: 0.95 | IL13: Quarter | IM13: Regular Cash
A14: 45463 | B14: 45464 | C14: 45464 | D14: 45504 | E14: 1.759024 | F14: Quarter | G14: Income | I14: 45464 | J14: 45467 | K14: 45467 | L14: 45504 | M14: 0.7615 | N14: Quarter | O14: Income | Q14: 45555 | R14: 45558 | S14: 45558 | T14: 45560 | U14: 0.199257 | V14: Quarter | W14: Income | Y14: 43819 | Z14: 43822 | AA14: 43823 | AB14: 43829 | AC14: 1.0611 | AD14: Annual | AE14: Income | AG14: 45414 | AH14: 45422 | AI14: 45425 | AJ14: 45428 | AK14: 0.25 | AL14: Quarter | AM14: Regular Cash | AW14: 45407 | AX14: 45453 | AY14: 45453 | AZ14: 45460 | BA14: 0.2 | BB14: Quarter | BC14: Regular Cash | BE14: 45442 | BF14: 45457 | BG14: 45457 | BH14: 45469 | BI14: 0.5 | BJ14: Quarter | BK14: Regular Cash | BM14: 45455 | BN14: 45519 | BO14: 45519 | BP14: 45547 | BQ14: 0.75 | BR14: Quarter | BS14: Regular Cash | CC14: 45434 | CD14: 45454 | CE14: 45454 | CF14: 45471 | CG14: 0.01 | CH14: Quarter | CI14: Regular Cash | DA14: 45422 | DB14: 45547 | DC14: 45547 | DD14: 45574 | DE14: 0.493613 | DF14: Quarter | DG14: Regular Cash | DI14: 45455 | DJ14: 45488 | DK14: 45484 | DL14: 45485 | DM14: 10 | DN14: None | DO14: Stock Split | DY14: 45371 | DZ14: 45379 | EA14: 45383 | EB14: 45398 | EC14: 0.115 | ED14: Quarter | EE14: Regular Cash | FU14: 45454 | FV14: 45484 | FW14: 45484 | FX14: 45498 | FY14: 0.4 | FZ14: Quarter | GA14: Regular Cash | GC14: 45470 | GD14: 45482 | GE14: 45482 | GF14: 45498 | GG14: 0.4 | GH14: Quarter | GI14: Regular Cash | HA14: 45418 | HB14: 45427 | HC14: 45428 | HD14: 45453 | HE14: 1.3 | HF14: Quarter | HG14: Regular Cash | HI14: 45448 | HJ14: 45460 | HK14: 45460 | HL14: 45468 | HM14: 2.1 | HN14: Quarter | HO14: Regular Cash | HQ14: 45432 | HR14: 45478 | HS14: 45478 | HT14: 45504 | HU14: 1.15 | HV14: Quarter | HW14: Regular Cash | HY14: 45392 | HZ14: 45407 | IA14: 45408 | IB14: 45422 | IC14: 1.16 | ID14: Quarter | IE14: Regular Cash | IG14: 45408 | IH14: 45426 | II14: 45427 | IJ14: 45453 | IK14: 0.95 | IL14: Quarter | IM14: Regular Cash
A15: 45365 | B15: 45366 | C15: 45369 | D15: 45412 | E15: 1.594937 | F15: Quarter | G15: Income | I15: 45366 | J15: 45369 | K15: 45370 | L15: 45412 | M15: 0.57345 | N15: Quarter | O15: Income | Q15: 45464 | R15: 45467 | S15: 45467 | T15: 45469 | U15: 0.200001 | V15: Quarter | W15: Income | Y15: 43453 | Z15: 43454 | AA15: 43455 | AB15: 43461 | AC15: 0.819 | AD15: Annual | AE15: Income | AG15: 45323 | AH15: 45331 | AI15: 45334 | AJ15: 45337 | AK15: 0.24 | AL15: Quarter | AM15: Regular Cash | AW15: 44557 | AX15: 44760 | AY15: 44743 | AZ15: 44757 | BA15: 20 | BB15: None | BC15: Stock Split | BE15: 45323 | BF15: 45343 | BG15: 45344 | BH15: 45377 | BI15: 0.5 | BJ15: Quarter | BK15: Regular Cash | BM15: 45363 | BN15: 45427 | BO15: 45428 | BP15: 45456 | BQ15: 0.75 | BR15: Quarter | BS15: Regular Cash | CC15: 45434 | CD15: 45453 | CE15: 45449 | CF15: 45450 | CG15: 10 | CH15: None | CI15: Stock Split | DA15: 45328 | DB15: 45456 | DC15: 45456 | DD15: 45484 | DE15: 0.42654 | DF15: Quarter | DG15: Regular Cash | DI15: 45455 | DJ15: 45467 | DK15: 45467 | DL15: 45471 | DM15: 0.525 | DN15: Quarter | DO15: Regular Cash | DY15: 45280 | DZ15: 45289 | EA15: 45293 | EB15: 45309 | EC15: 0.115 | ED15: Quarter | EE15: Regular Cash | FU15: 45362 | FV15: 45391 | FW15: 45392 | FX15: 45406 | FY15: 0.4 | FZ15: Quarter | GA15: Regular Cash | GC15: 45350 | GD15: 45364 | GE15: 45365 | GF15: 45393 | GG15: 0.4 | GH15: Quarter | GI15: Regular Cash | HA15: 45268 | HB15: 45336 | HC15: 45337 | HD15: 45359 | HE15: 1.3 | HF15: Quarter | HG15: Regular Cash | HI15: 45345 | HJ15: 45359 | HK15: 45362 | HL15: 45370 | HM15: 1.88 | HN15: Quarter | HO15: Regular Cash | HQ15: 45370 | HR15: 45386 | HS15: 45387 | HT15: 45412 | HU15: 1.15 | HV15: Quarter | HW15: Regular Cash | HY15: 45309 | HZ15: 45323 | IA15: 45324 | IB15: 45338 | IC15: 1.02 | ID15: Quarter | IE15: Regular Cash | IG15: 45324 | IH15: 45335 | II15: 45336 | IJ15: 45362 | IK15: 0.95 | IL15: Quarter | IM15: Regular Cash
A16: 45274 | B16: 45275 | C16: 45278 | D16: 45322 | E16: 1.906073 | F16: Quarter | G16: Income | I16: 45286 | J16: 45287 | K16: 45288 | L16: 45306 | M16: 0.21584 | N16: None | O16: Special Cash | Q16: 45366 | R16: 45369 | S16: 45370 | T16: 45372 | U16: 0.1696 | V16: Quarter | W16: Income | Y16: 43084 | Z16: 43087 | AA16: 43088 | AB16: 43091 | AC16: 0.698 | AD16: Annual | AE16: Income | AG16: 45232 | AH16: 45240 | AI16: 45243 | AJ16: 45246 | AK16: 0.24 | AL16: Quarter | AM16: Regular Cash | AW16: 41011 | AX16: 41732 | AY16: 41725 | AZ16: 41731 | BA16: 1 | BB16: None | BC16: In-specie | BE16: 40940 | BF16: 40482 | BG16: #N/A N/A | BH16: #N/A N/A | BI16: 5 | BJ16: None | BK16: Stock Split | BM16: 45258 | BN16: 45336 | BO16: 45337 | BP16: 45365 | BQ16: 0.75 | BR16: Quarter | BS16: Regular Cash | CC16: 45343 | CD16: 45356 | CE16: 45357 | CF16: 45378 | CG16: 0.004 | CH16: Quarter | CI16: Regular Cash | DA16: 45244 | DB16: 45369 | DC16: 45370 | DD16: 45393 | DE16: 0.431022 | DF16: Quarter | DG16: Regular Cash | DI16: 45358 | DJ16: 45371 | DK16: 45372 | DL16: 45380 | DM16: 0.525 | DN16: Quarter | DO16: Regular Cash | DY16: 45196 | DZ16: 45205 | EA16: 45209 | EB16: 45224 | EC16: 0.115 | ED16: Quarter | EE16: Regular Cash | FU16: 45271 | FV16: 45301 | FW16: 45302 | FX16: 45316 | FY16: 0.4 | FZ16: Quarter | GA16: Regular Cash | GC16: 41299 | GD16: 41382 | GE16: 41367 | GF16: 41381 | GG16: 4 | GH16: None | GI16: Stock Split | HA16: 45231 | HB16: 45244 | HC16: 45245 | HD16: 45268 | HE16: 1.13 | HF16: Quarter | HG16: Regular Cash | HI16: 45238 | HJ16: 45261 | HK16: 45264 | HL16: 45272 | HM16: 1.88 | HN16: Quarter | HO16: Regular Cash | HQ16: 45272 | HR16: 45295 | HS16: 45296 | HT16: 45322 | HU16: 1.05 | HV16: Quarter | HW16: Regular Cash | HY16: 45275 | HZ16: 45287 | IA16: 45288 | IB16: 45303 | IC16: 15 | ID16: None | IE16: Special Cash | IG16: 45226 | IH16: 45244 | II16: 45245 | IJ16: 45271 | IK16: 0.95 | IL16: Quarter | IM16: Regular Cash
A17: 45183 | B17: 45184 | C17: 45187 | D17: 45230 | E17: 1.583169 | F17: Quarter | G17: Income | I17: 45275 | J17: 45278 | K17: 45279 | L17: 45289 | M17: 0.80826 | N17: Quarter | O17: Income | Q17: 45275 | R17: 45278 | S17: 45279 | T17: 45281 | U17: 0.211007 | V17: Quarter | W17: Income | Y17: 42720 | Z17: 42723 | AA17: 42725 | AB17: 42727 | AC17: 0.288 | AD17: Annual | AE17: Income | AG17: 45141 | AH17: 45149 | AI17: 45152 | AJ17: 45155 | AK17: 0.24 | AL17: Quarter | AM17: Regular Cash | BM17: 45188 | BN17: 45245 | BO17: 45246 | BP17: 45274 | BQ17: 0.75 | BR17: Quarter | BS17: Regular Cash | CC17: 45251 | CD17: 45265 | CE17: 45266 | CF17: 45288 | CG17: 0.004 | CH17: Quarter | CI17: Regular Cash | DA17: 45146 | DB17: 45274 | DC17: 45275 | DD17: 45302 | DE17: 0.381765 | DF17: Quarter | DG17: Regular Cash | DI17: 45267 | DJ17: 45279 | DK17: 45280 | DL17: 45289 | DM17: 0.525 | DN17: Quarter | DO17: Regular Cash | DY17: 45105 | DZ17: 45114 | EA17: 45117 | EB17: 45132 | EC17: 0.115 | ED17: Quarter | EE17: Regular Cash | FU17: 45180 | FV17: 45210 | FW17: 45211 | FX17: 45225 | FY17: 0.4 | FZ17: Quarter | GA17: Regular Cash | HA17: 45103 | HB17: 45152 | HC17: 45153 | HD17: 45177 | HE17: 1.13 | HF17: Quarter | HG17: Regular Cash | HI17: 45161 | HJ17: 45177 | HK17: 45180 | HL17: 45188 | HM17: 1.88 | HN17: Quarter | HO17: Regular Cash | HQ17: 45188 | HR17: 45204 | HS17: 45205 | HT17: 45230 | HU17: 1.05 | HV17: Quarter | HW17: Regular Cash | HY17: 45217 | HZ17: 45232 | IA17: 45233 | IB17: 45247 | IC17: 1.02 | ID17: Quarter | IE17: Regular Cash | IG17: 45135 | IH17: 45153 | II17: 45154 | IJ17: 45180 | IK17: 0.91 | IL17: Quarter | IM17: Regular Cash
A18: 45092 | B18: 45093 | C18: 45097 | D18: 45138 | E18: 1.638367 | F18: Quarter | G18: Income | I18: 45184 | J18: 45187 | K18: 45188 | L18: 45230 | M18: 0.53555 | N18: Quarter | O18: Income | Q18: 45184 | R18: 45187 | S18: 45188 | T18: 45190 | U18: 0.180143 | V18: Quarter | W18: Income | Y18: 42356 | Z18: 42359 | AA18: 42361 | AB18: 42366 | AC18: 0.5705 | AD18: Annual | AE18: Income | AG18: 45050 | AH18: 45058 | AI18: 45061 | AJ18: 45064 | AK18: 0.24 | AL18: Quarter | AM18: Regular Cash | BM18: 45090 | BN18: 45154 | BO18: 45155 | BP18: 45183 | BQ18: 0.68 | BR18: Quarter | BS18: Regular Cash | CC18: 45161 | CD18: 45175 | CE18: 45176 | CF18: 45197 | CG18: 0.004 | CH18: Quarter | CI18: Regular Cash | DA18: 45055 | DB18: 45183 | DC18: 45184 | DD18: 45211 | DE18: 0.367441 | DF18: Quarter | DG18: Regular Cash | DI18: 45169 | DJ18: 45189 | DK18: 45190 | DL18: 45198 | DM18: 0.46 | DN18: Quarter | DO18: Regular Cash | DY18: 45013 | DZ18: 45022 | EA18: 45026 | EB18: 45041 | EC18: 0.115 | ED18: Quarter | EE18: Regular Cash | FU18: 45089 | FV18: 45118 | FW18: 45119 | FX18: 45133 | FY18: 0.4 | FZ18: Quarter | GA18: Regular Cash | HA18: 45047 | HB18: 45058 | HC18: 45061 | HD18: 45086 | HE18: 1.13 | HF18: Quarter | HG18: Regular Cash | HI18: 45084 | HJ18: 45092 | HK18: 45096 | HL18: 45104 | HM18: 1.88 | HN18: Quarter | HO18: Regular Cash | HQ18: 45061 | HR18: 45112 | HS18: 45113 | HT18: 45138 | HU18: 1 | HV18: Quarter | HW18: Regular Cash | HY18: 45147 | HZ18: 45162 | IA18: 45163 | IB18: 45177 | IC18: 1.02 | ID18: Quarter | IE18: Regular Cash | IG18: 45044 | IH18: 45061 | II18: 45062 | IJ18: 45086 | IK18: 0.91 | IL18: Quarter | IM18: Regular Cash
A19: 45001 | B19: 45002 | C19: 45005 | D19: 45044 | E19: 1.506204 | F19: Quarter | G19: Income | I19: 45093 | J19: 45097 | K19: 45098 | L19: 45138 | M19: 0.50395 | N19: Quarter | O19: Income | Q19: 45093 | R19: 45097 | S19: 45098 | T19: 45100 | U19: 0.180792 | V19: Quarter | W19: Income | Y19: 41992 | Z19: 41995 | AA19: 41997 | AB19: 42002 | AC19: 0.316 | AD19: Annual | AE19: Income | AG19: 44959 | AH19: 44967 | AI19: 44970 | AJ19: 44973 | AK19: 0.23 | AL19: Quarter | AM19: Regular Cash | BM19: 44999 | BN19: 45063 | BO19: 45064 | BP19: 45085 | BQ19: 0.68 | BR19: Quarter | BS19: Regular Cash | CC19: 45070 | CD19: 45084 | CE19: 45085 | CF19: 45107 | CG19: 0.004 | CH19: Quarter | CI19: Regular Cash | DA19: 44971 | DB19: 45092 | DC19: 45093 | DD19: 45120 | DE19: 0.3468 | DF19: Quarter | DG19: Regular Cash | DI19: 45078 | DJ19: 45098 | DK19: 45099 | DL19: 45107 | DM19: 0.46 | DN19: Quarter | DO19: Regular Cash | DY19: 44916 | DZ19: 44925 | EA19: 44929 | EB19: 44945 | EC19: 0.115 | ED19: Quarter | EE19: Regular Cash | FU19: 44994 | FV19: 45026 | FW19: 45027 | FX19: 45040 | FY19: 0.4 | FZ19: Quarter | GA19: Regular Cash | HA19: 44907 | HB19: 44971 | HC19: 44972 | HD19: 44995 | HE19: 1.13 | HF19: Quarter | HG19: Regular Cash | HI19: 44984 | HJ19: 44995 | HK19: 44998 | HL19: 45006 | HM19: 1.65 | HN19: Quarter | HO19: Regular Cash | HQ19: 45006 | HR19: 45021 | HS19: 45022 | HT19: 45046 | HU19: 1 | HV19: Quarter | HW19: Regular Cash | HY19: 45035 | HZ19: 45050 | IA19: 45051 | IB19: 45065 | IC19: 1.02 | ID19: Quarter | IE19: Regular Cash | IG19: 44957 | IH19: 44970 | II19: 44971 | IJ19: 44995 | IK19: 0.91 | IL19: Quarter | IM19: Regular Cash
A20: 44910 | B20: 44911 | C20: 44914 | D20: 44957 | E20: 1.7814 | F20: Quarter | G20: Income | I20: 45002 | J20: 45005 | K20: 45006 | L20: 45044 | M20: 0.47223 | N20: Quarter | O20: Income | Q20: 45002 | R20: 45005 | S20: 45006 | T20: 45008 | U20: 0.157726 | V20: Quarter | W20: Income | Y20: 41628 | Z20: 41631 | AA20: 41634 | AB20: 41638 | AC20: 0.3295 | AD20: Annual | AE20: Income | AG20: 44861 | AH20: 44869 | AI20: 44872 | AJ20: 44875 | AK20: 0.23 | AL20: Quarter | AM20: Regular Cash | BM20: 44894 | BN20: 44972 | BO20: 44973 | BP20: 44994 | BQ20: 0.68 | BR20: Quarter | BS20: Regular Cash | CC20: 44979 | CD20: 44992 | CE20: 44993 | CF20: 45014 | CG20: 0.004 | CH20: Quarter | CI20: Regular Cash | DA20: 44873 | DB20: 45001 | DC20: 45002 | DD20: 45029 | DE20: 0.356346 | DF20: Quarter | DG20: Regular Cash | DI20: 44987 | DJ20: 45006 | DK20: 45007 | DL20: 45016 | DM20: 0.46 | DN20: Quarter | DO20: Regular Cash | DY20: 44833 | DZ20: 44841 | EA20: 44845 | EB20: 44860 | EC20: 0.115 | ED20: Quarter | EE20: Regular Cash | FU20: 44907 | FV20: 44935 | FW20: 44936 | FX20: 44950 | FY20: 0.32 | FZ20: Quarter | GA20: Regular Cash | HA20: 44851 | HB20: 44879 | HC20: 44880 | HD20: 44904 | HE20: 0.98 | HF20: Quarter | HG20: Regular Cash | HI20: 44869 | HJ20: 44897 | HK20: 44900 | HL20: 44908 | HM20: 1.65 | HN20: Quarter | HO20: Regular Cash | HQ20: 44908 | HR20: 44931 | HS20: 44932 | HT20: 44957 | HU20: 1 | HV20: Quarter | HW20: Regular Cash | HY20: 44945 | HZ20: 44959 | IA20: 44960 | IB20: 44974 | IC20: 0.9 | ID20: Quarter | IE20: Regular Cash | IG20: 44862 | IH20: 44879 | II20: 44880 | IJ20: 44904 | IK20: 0.91 | IL20: Quarter | IM20: Regular Cash
A21: 44819 | B21: 44820 | C21: 44823 | D21: 44865 | E21: 1.596398 | F21: Quarter | G21: Income | I21: 44911 | J21: 44914 | K21: 44915 | L21: 44925 | M21: 0.65541 | N21: Quarter | O21: Income | Q21: 44911 | R21: 44914 | S21: 44915 | T21: 44917 | U21: 0.182682 | V21: Quarter | W21: Income | Y21: 41264 | Z21: 41267 | AA21: 41270 | AB21: 41274 | AC21: 0.35 | AD21: Annual | AE21: Income | AG21: 44770 | AH21: 44778 | AI21: 44781 | AJ21: 44784 | AK21: 0.23 | AL21: Quarter | AM21: Regular Cash | BM21: 44824 | BN21: 44881 | BO21: 44882 | BP21: 44903 | BQ21: 0.68 | BR21: Quarter | BS21: Regular Cash | CC21: 44881 | CD21: 44895 | CE21: 44896 | CF21: 44917 | CG21: 0.004 | CH21: Quarter | CI21: Regular Cash | DA21: 44782 | DB21: 44910 | DC21: 44911 | DD21: 44938 | DE21: 0.353366 | DF21: Quarter | DG21: Regular Cash | DI21: 44903 | DJ21: 44914 | DK21: 44915 | DL21: 44925 | DM21: 0.46 | DN21: Quarter | DO21: Regular Cash | DY21: 44742 | DZ21: 44750 | EA21: 44753 | EB21: 44768 | EC21: 0.115 | ED21: Quarter | EE21: Regular Cash | FU21: 44816 | FV21: 44845 | FW21: 44846 | FX21: 44859 | FY21: 0.32 | FZ21: Quarter | GA21: Regular Cash | HA21: 44739 | HB21: 44785 | HC21: 44788 | HD21: 44813 | HE21: 0.98 | HF21: Quarter | HG21: Regular Cash | HI21: 44790 | HJ21: 44813 | HK21: 44816 | HL21: 44824 | HM21: 1.65 | HN21: Quarter | HO21: Regular Cash | HQ21: 44824 | HR21: 44839 | HS21: 44840 | HT21: 44865 | HU21: 1 | HV21: Quarter | HW21: Regular Cash | HY21: 44846 | HZ21: 44861 | IA21: 44862 | IB21: 44875 | IC21: 0.9 | ID21: Quarter | IE21: Regular Cash | IG21: 44769 | IH21: 44784 | II21: 44785 | IJ21: 44813 | IK21: 0.88 | IL21: Quarter | IM21: Regular Cash
A22: 44728 | B22: 44729 | C22: 44733 | D22: 44771 | E22: 1.576871 | F22: Quarter | G22: Income | I22: 44820 | J22: 44823 | K22: 44824 | L22: 44865 | M22: 0.51856 | N22: Quarter | O22: Income | Q22: 44820 | R22: 44823 | S22: 44824 | T22: 44826 | U22: 0.158333 | V22: Quarter | W22: Income | AG22: 44679 | AH22: 44687 | AI22: 44690 | AJ22: 44693 | AK22: 0.23 | AL22: Quarter | AM22: Regular Cash | BM22: 44726 | BN22: 44790 | BO22: 44791 | BP22: 44812 | BQ22: 0.62 | BR22: Quarter | BS22: Regular Cash | CC22: 44797 | CD22: 44811 | CE22: 44812 | CF22: 44833 | CG22: 0.004 | CH22: Quarter | CI22: Regular Cash | DA22: 44691 | DB22: 44819 | DC22: 44820 | DD22: 44847 | DE22: 0.343565 | DF22: Quarter | DG22: Regular Cash | DI22: 44805 | DJ22: 44825 | DK22: 44826 | DL22: 44834 | DM22: 0.41 | DN22: Quarter | DO22: Regular Cash | DY22: 44649 | DZ22: 44659 | EA22: 44662 | EB22: 44677 | EC22: 0.1 | ED22: Quarter | EE22: Regular Cash | FU22: 44725 | FV22: 44753 | FW22: 44754 | FX22: 44768 | FY22: 0.32 | FZ22: Quarter | GA22: Regular Cash | HA22: 44683 | HB22: 44694 | HC22: 44697 | HD22: 44722 | HE22: 0.98 | HF22: Quarter | HG22: Regular Cash | HI22: 44720 | HJ22: 44728 | HK22: 44732 | HL22: 44740 | HM22: 1.65 | HN22: Quarter | HO22: Regular Cash | HQ22: 44697 | HR22: 44747 | HS22: 44748 | HT22: 44773 | HU22: 1 | HV22: Quarter | HW22: Regular Cash | HY22: 44755 | HZ22: 44770 | IA22: 44771 | IB22: 44785 | IC22: 0.9 | ID22: Quarter | IE22: Regular Cash | IG22: 44678 | IH22: 44693 | II22: 44694 | IJ22: 44722 | IK22: 0.88 | IL22: Quarter | IM22: Regular Cash
A23: 44637 | B23: 44638 | C23: 44641 | D23: 44680 | E23: 1.366009 | F23: Quarter | G23: Income | I23: 44729 | J23: 44733 | K23: 44734 | L23: 44771 | M23: 0.5274 | N23: Quarter | O23: Income | Q23: 44729 | R23: 44733 | S23: 44734 | T23: 44736 | U23: 0.161584 | V23: Quarter | W23: Income | AG23: 44588 | AH23: 44596 | AI23: 44599 | AJ23: 44602 | AK23: 0.22 | AL23: Quarter | AM23: Regular Cash | BM23: 44634 | BN23: 44699 | BO23: 44700 | BP23: 44721 | BQ23: 0.62 | BR23: Quarter | BS23: Regular Cash | CC23: 44706 | CD23: 44720 | CE23: 44721 | CF23: 44743 | CG23: 0.004 | CH23: Quarter | CI23: Regular Cash | DA23: 44607 | DB23: 44728 | DC23: 44729 | DD23: 44756 | DE23: 0.364647 | DF23: Quarter | DG23: Regular Cash | DI23: 44707 | DJ23: 44733 | DK23: 44734 | DL23: 44742 | DM23: 0.41 | DN23: Quarter | DO23: Regular Cash | DY23: 44550 | DZ23: 44561 | EA23: 44564 | EB23: 44579 | EC23: 0.1 | ED23: Quarter | EE23: Regular Cash | FU23: 44630 | FV23: 44658 | FW23: 44659 | FX23: 44672 | FY23: 0.32 | FZ23: Quarter | GA23: Regular Cash | HA23: 44543 | HB23: 44606 | HC23: 44607 | HD23: 44630 | HE23: 0.98 | HF23: Quarter | HG23: Regular Cash | HI23: 44608 | HJ23: 44631 | HK23: 44634 | HL23: 44642 | HM23: 1.45 | HN23: Quarter | HO23: Regular Cash | HQ23: 44635 | HR23: 44656 | HS23: 44657 | HT23: 44681 | HU23: 1 | HV23: Quarter | HW23: Regular Cash | HY23: 44664 | HZ23: 44679 | IA23: 44680 | IB23: 44694 | IC23: 0.9 | ID23: Quarter | IE23: Regular Cash | IG23: 44587 | IH23: 44601 | II23: 44602 | IJ23: 44630 | IK23: 0.88 | IL23: Quarter | IM23: Regular Cash
A24: 44546 | B24: 44547 | C24: 44550 | D24: 44592 | E24: 1.636431 | F24: Quarter | G24: Income | I24: 44638 | J24: 44641 | K24: 44642 | L24: 44680 | M24: 0.43369 | N24: Quarter | O24: Income | Q24: 44638 | R24: 44641 | S24: 44642 | T24: 44644 | U24: 0.14281 | V24: Quarter | W24: Income | AG24: 44497 | AH24: 44505 | AI24: 44508 | AJ24: 44511 | AK24: 0.22 | AL24: Quarter | AM24: Regular Cash | BM24: 44537 | BN24: 44608 | BO24: 44609 | BP24: 44630 | BQ24: 0.62 | BR24: Quarter | BS24: Regular Cash | CC24: 44608 | CD24: 44622 | CE24: 44623 | CF24: 44644 | CG24: 0.004 | CH24: Quarter | CI24: Regular Cash | DA24: 44509 | DB24: 44636 | DC24: 44637 | DD24: 44665 | DE24: 0.375734 | DF24: Quarter | DG24: Regular Cash | DI24: 44623 | DJ24: 44641 | DK24: 44642 | DL24: 44651 | DM24: 0.41 | DN24: Quarter | DO24: Regular Cash | DY24: 44410 | DZ24: 44469 | EA24: 44470 | EB24: 44487 | EC24: 0.1 | ED24: Quarter | EE24: Regular Cash | FU24: 44539 | FV24: 44567 | FW24: 44568 | FX24: 44580 | FY24: 0.32 | FZ24: Quarter | GA24: Regular Cash | HA24: 44487 | HB24: 44512 | HC24: 44515 | HD24: 44540 | HE24: 0.85 | HF24: Quarter | HG24: Regular Cash | HI24: 44505 | HJ24: 44533 | HK24: 44536 | HL24: 44544 | HM24: 1.45 | HN24: Quarter | HO24: Regular Cash | HQ24: 44544 | HR24: 44566 | HS24: 44567 | HT24: 44592 | HU24: 1 | HV24: Quarter | HW24: Regular Cash | HY24: 44581 | HZ24: 44595 | IA24: 44596 | IB24: 44610 | IC24: 0.79 | ID24: Quarter | IE24: Regular Cash | IG24: 44496 | IH24: 44510 | II24: 44512 | IJ24: 44540 | IK24: 0.88 | IL24: Quarter | IM24: Regular Cash
A25: 44455 | B25: 44456 | C25: 44459 | D25: 44498 | E25: 1.428117 | F25: Quarter | G25: Income | I25: 44547 | J25: 44550 | K25: 44551 | L25: 44561 | M25: 0.49141 | N25: Quarter | O25: Income | Q25: 44547 | R25: 44550 | S25: 44551 | T25: 44553 | U25: 0.158272 | V25: Quarter | W25: Income | AG25: 44404 | AH25: 44414 | AI25: 44417 | AJ25: 44420 | AK25: 0.22 | AL25: Quarter | AM25: Regular Cash | BM25: 44453 | BN25: 44517 | BO25: 44518 | BP25: 44539 | BQ25: 0.62 | BR25: Quarter | BS25: Regular Cash | CC25: 44517 | CD25: 44531 | CE25: 44532 | CF25: 44553 | CG25: 0.004 | CH25: Quarter | CI25: Regular Cash | DA25: 44419 | DB25: 44546 | DC25: 44547 | DD25: 44574 | DE25: 0.392615 | DF25: Quarter | DG25: Regular Cash | DI25: 44539 | DJ25: 44551 | DK25: 44552 | DL25: 44561 | DM25: 0.41 | DN25: Quarter | DO25: Regular Cash | DY25: 42571 | DZ25: 42571 | EA25: 42583 | EB25: #N/A N/A | EC25: 1 | ED25: None | EE25: Poison Pill Rights | FU25: 44452 | FV25: 44477 | FW25: 44481 | FX25: 44495 | FY25: 0.32 | FZ25: Quarter | GA25: Regular Cash | HA25: 44376 | HB25: 44420 | HC25: 44421 | HD25: 44449 | HE25: 0.85 | HF25: Quarter | HG25: Regular Cash | HI25: 44419 | HJ25: 44449 | HK25: 44452 | HL25: 44460 | HM25: 1.45 | HN25: Quarter | HO25: Regular Cash | HQ25: 44460 | HR25: 44474 | HS25: 44475 | HT25: 44500 | HU25: 1 | HV25: Quarter | HW25: Regular Cash | HY25: 44482 | HZ25: 44497 | IA25: 44498 | IB25: 44512 | IC25: 0.79 | ID25: Quarter | IE25: Regular Cash | IG25: 44405 | IH25: 44420 | II25: 44421 | IJ25: 44449 | IK25: 0.87 | IL25: Quarter | IM25: Regular Cash
A26: 44364 | B26: 44365 | C26: 44368 | D26: 44407 | E26: 1.375875 | F26: Quarter | G26: Income | I26: 44456 | J26: 44459 | K26: 44460 | L26: 44498 | M26: 0.41391 | N26: Quarter | O26: Income | Q26: 44456 | R26: 44459 | S26: 44460 | T26: 44462 | U26: 0.136431 | V26: Quarter | W26: Income | AG26: 44314 | AH26: 44323 | AI26: 44326 | AJ26: 44329 | AK26: 0.22 | AL26: Quarter | AM26: Regular Cash | BM26: 44363 | BN26: 44426 | BO26: 44427 | BP26: 44448 | BQ26: 0.56 | BR26: Quarter | BS26: Regular Cash | CC26: 44426 | CD26: 44439 | CE26: 44440 | CF26: 44462 | CG26: 0.004 | CH26: Quarter | CI26: Regular Cash | DA26: 44357 | DB26: 44455 | DC26: 44456 | DD26: 44483 | DE26: 0.388084 | DF26: Quarter | DG26: Regular Cash | DI26: 44441 | DJ26: 44460 | DK26: 44461 | DL26: 44469 | DM26: 0.36 | DN26: Quarter | DO26: Regular Cash | FU26: 44362 | FV26: 44391 | FW26: 44392 | FX26: 44406 | FY26: 0.32 | FZ26: Quarter | GA26: Regular Cash | HA26: 44319 | HB26: 44329 | HC26: 44330 | HD26: 44357 | HE26: 0.85 | HF26: Quarter | HG26: Regular Cash | HI26: 44356 | HJ26: 44365 | HK26: 44368 | HL26: 44376 | HM26: 1.45 | HN26: Quarter | HO26: Regular Cash | HQ26: 44333 | HR26: 44379 | HS26: 44383 | HT26: 44408 | HU26: 0.9 | HV26: Quarter | HW26: Regular Cash | HY26: 44390 | HZ26: 44406 | IA26: 44407 | IB26: 44421 | IC26: 0.79 | ID26: Quarter | IE26: Regular Cash | IG26: 44314 | IH26: 44328 | II26: 44329 | IJ26: 44357 | IK26: 0.87 | IL26: Quarter | IM26: Regular Cash
A27: 44273 | B27: 44274 | C27: 44277 | D27: 44316 | E27: 1.277788 | F27: Quarter | G27: Income | I27: 44365 | J27: 44368 | K27: 44369 | L27: 44407 | M27: 0.39679 | N27: Quarter | O27: Income | Q27: 44365 | R27: 44368 | S27: 44369 | T27: 44371 | U27: 0.129746 | V27: Quarter | W27: Income | AG27: 44223 | AH27: 44232 | AI27: 44235 | AJ27: 44238 | AK27: 0.205 | AL27: Quarter | AM27: Regular Cash | BM27: 44271 | BN27: 44335 | BO27: 44336 | BP27: 44357 | BQ27: 0.56 | BR27: Quarter | BS27: Regular Cash | CC27: 44337 | CD27: 44397 | CE27: 44368 | CF27: 44396 | CG27: 3 | CH27: None | CI27: Stock Dividend | DA27: 44236 | DB27: 44364 | DC27: 44365 | DD27: 44392 | DE27: 0.352025 | DF27: Quarter | DG27: Regular Cash | DI27: 44350 | DJ27: 44368 | DK27: 44369 | DL27: 44377 | DM27: 0.36 | DN27: Quarter | DO27: Regular Cash | FU27: 44265 | FV27: 44293 | FW27: 44294 | FX27: 44308 | FY27: 0.32 | FZ27: Quarter | GA27: Regular Cash | HA27: 44179 | HB27: 44238 | HC27: 44239 | HD27: 44265 | HE27: 0.85 | HF27: Quarter | HG27: Regular Cash | HI27: 44251 | HJ27: 44267 | HK27: 44270 | HL27: 44278 | HM27: 1.25 | HN27: Quarter | HO27: Regular Cash | HQ27: 44271 | HR27: 44291 | HS27: 44292 | HT27: 44316 | HU27: 0.9 | HV27: Quarter | HW27: Regular Cash | HY27: 44300 | HZ27: 44315 | IA27: 44316 | IB27: 44330 | IC27: 0.79 | ID27: Quarter | IE27: Regular Cash | IG27: 44223 | IH27: 44236 | II27: 44237 | IJ27: 44265 | IK27: 0.87 | IL27: Quarter | IM27: Regular Cash
A28: 44182 | B28: 44183 | C28: 44186 | D28: 44225 | E28: 1.58 | F28: Quarter | G28: Income | I28: 44274 | J28: 44277 | K28: 44278 | L28: 44316 | M28: 0.39468 | N28: Quarter | O28: Income | Q28: 44274 | R28: 44277 | S28: 44278 | T28: 44280 | U28: 0.136575 | V28: Quarter | W28: Income | AG28: 44133 | AH28: 44141 | AI28: 44144 | AJ28: 44147 | AK28: 0.205 | AL28: Quarter | AM28: Regular Cash | BM28: 44167 | BN28: 44244 | BO28: 44245 | BP28: 44266 | BQ28: 0.56 | BR28: Quarter | BS28: Regular Cash | CC28: 44342 | CD28: 44356 | CE28: 44357 | CF28: 44378 | CG28: 0.004 | CH28: Quarter | CI28: Regular Cash | DA28: 44145 | DB28: 44272 | DC28: 44273 | DD28: 44301 | DE28: 0.347478 | DF28: Quarter | DG28: Regular Cash | DI28: 44259 | DJ28: 44274 | DK28: 44277 | DL28: 44286 | DM28: 0.36 | DN28: Quarter | DO28: Regular Cash | FU28: 44175 | FV28: 44202 | FW28: 44203 | FX28: 44217 | FY28: 0.24 | FZ28: Quarter | GA28: Regular Cash | HA28: 44123 | HB28: 44147 | HC28: 44148 | HD28: 44175 | HE28: 0.74 | HF28: Quarter | HG28: Regular Cash | HI28: 44139 | HJ28: 44169 | HK28: 44172 | HL28: 44180 | HM28: 1.25 | HN28: Quarter | HO28: Regular Cash | HQ28: 44173 | HR28: 44201 | HS28: 44202 | HT28: 44227 | HU28: 0.9 | HV28: Quarter | HW28: Regular Cash | HY28: 44217 | HZ28: 44231 | IA28: 44232 | IB28: 44246 | IC28: 0.7 | ID28: Quarter | IE28: Regular Cash | IG28: 44132 | IH28: 44145 | II28: 44147 | IJ28: 44175 | IK28: 0.87 | IL28: Quarter | IM28: Regular Cash
A29: 44091 | B29: 44092 | C29: 44095 | D29: 44134 | E29: 1.339224 | F29: Quarter | G29: Income | I29: 44183 | J29: 44186 | K29: 44187 | L29: 44196 | M29: 0.56133 | N29: Quarter | O29: Income | Q29: 44183 | R29: 44186 | S29: 44187 | T29: 44189 | U29: 0.148821 | V29: Quarter | W29: Income | AG29: 44042 | AH29: 44074 | AI29: 44067 | AJ29: 44071 | AK29: 4 | AL29: None | AM29: Stock Split | BM29: 44089 | BN29: 44153 | BO29: 44154 | BP29: 44175 | BQ29: 0.56 | BR29: Quarter | BS29: Regular Cash | CC29: 44251 | CD29: 44264 | CE29: 44265 | CF29: 44286 | CG29: 0.004 | CH29: Quarter | CI29: Regular Cash | DA29: 44055 | DB29: 44182 | DC29: 44183 | DD29: 44210 | DE29: 0.352678 | DF29: Quarter | DG29: Regular Cash | DI29: 44175 | DJ29: 44183 | DK29: 44186 | DL29: 44196 | DM29: 0.36 | DN29: Quarter | DO29: Regular Cash | FU29: 44084 | FV29: 44111 | FW29: 44112 | FX29: 44126 | FY29: 0.24 | FZ29: Quarter | GA29: Regular Cash | HA29: 44027 | HB29: 44056 | HC29: 44057 | HD29: 44084 | HE29: 0.74 | HF29: Quarter | HG29: Regular Cash | HI29: 44048 | HJ29: 44085 | HK29: 44088 | HL29: 44096 | HM29: 1.25 | HN29: Quarter | HO29: Regular Cash | HQ29: 44089 | HR29: 44109 | HS29: 44110 | HT29: 44135 | HU29: 0.9 | HV29: Quarter | HW29: Regular Cash | HY29: 44151 | HZ29: 44166 | IA29: 44167 | IB29: 44176 | IC29: 10 | ID29: None | IE29: Special Cash | IG29: 44041 | IH29: 44055 | II29: 44056 | IJ29: 44084 | IK29: 0.87 | IL29: Quarter | IM29: Regular Cash
A30: 44000 | B30: 44001 | C30: 44004 | D30: 44043 | E30: 1.366242 | F30: Quarter | G30: Income | I30: 44092 | J30: 44095 | K30: 44096 | L30: 44134 | M30: 0.38824 | N30: Quarter | O30: Income | Q30: 44092 | R30: 44095 | S30: 44096 | T30: 44098 | U30: 0.123263 | V30: Quarter | W30: Income | AG30: 44042 | AH30: 44050 | AI30: 44053 | AJ30: 44056 | AK30: 0.205 | AL30: Quarter | AM30: Regular Cash | BM30: 43999 | BN30: 44062 | BO30: 44063 | BP30: 44084 | BQ30: 0.51 | BR30: Quarter | BS30: Regular Cash | CC30: 44153 | CD30: 44168 | CE30: 44169 | CF30: 44194 | CG30: 0.004 | CH30: Quarter | CI30: Regular Cash | DA30: 43965 | DB30: 44091 | DC30: 44092 | DD30: 44119 | DE30: 0.343669 | DF30: Quarter | DG30: Regular Cash | DI30: 44077 | DJ30: 44095 | DK30: 44096 | DL30: 44104 | DM30: 0.325 | DN30: Quarter | DO30: Regular Cash | FU30: 43998 | FV30: 44026 | FW30: 44027 | FX30: 44040 | FY30: 0.24 | FZ30: Quarter | GA30: Regular Cash | HA30: 43955 | HB30: 43965 | HC30: 43966 | HD30: 43992 | HE30: 0.74 | HF30: Quarter | HG30: Regular Cash | HI30: 43983 | HJ30: 44001 | HK30: 44004 | HL30: 44012 | HM30: 1.25 | HN30: Quarter | HO30: Regular Cash | HQ30: 43969 | HR30: 44014 | HS30: 44018 | HT30: 44043 | HU30: 0.9 | HV30: Quarter | HW30: Regular Cash | HY30: 44118 | HZ30: 44133 | IA30: 44134 | IB30: 44148 | IC30: 0.7 | ID30: Quarter | IE30: Regular Cash | IG30: 43950 | IH30: 43963 | II30: 43964 | IJ30: 43992 | IK30: 0.87 | IL30: Quarter | IM30: Regular Cash
A31: 43909 | B31: 43910 | C31: 43913 | D31: 43951 | E31: 1.405559 | F31: Quarter | G31: Income | I31: 44001 | J31: 44004 | K31: 44005 | L31: 44043 | M31: 0.42426 | N31: Quarter | O31: Income | Q31: 44001 | R31: 44004 | S31: 44005 | T31: 44007 | U31: 0.140259 | V31: Quarter | W31: Income | AG31: 43951 | AH31: 43959 | AI31: 43962 | AJ31: 43965 | AK31: 0.205 | AL31: Quarter | AM31: Regular Cash | BM31: 43899 | BN31: 43971 | BO31: 43972 | BP31: 43993 | BQ31: 0.51 | BR31: Quarter | BS31: Regular Cash | CC31: 44062 | CD31: 44075 | CE31: 44076 | CF31: 44098 | CG31: 0.004 | CH31: Quarter | CI31: Regular Cash | DA31: 43873 | DB31: 44000 | DC31: 44001 | DD31: 44028 | DE31: 0.334859 | DF31: Quarter | DG31: Regular Cash | DI31: 43986 | DJ31: 44001 | DK31: 44004 | DL31: 44012 | DM31: 0.325 | DN31: Quarter | DO31: Regular Cash | FU31: 43902 | FV31: 43929 | FW31: 43930 | FX31: 43944 | FY31: 0.24 | FZ31: Quarter | GA31: Regular Cash | HA31: 43815 | HB31: 43874 | HC31: 43875 | HD31: 43900 | HE31: 0.74 | HF31: Quarter | HG31: Regular Cash | HI31: 43878 | HJ31: 43903 | HK31: 43906 | HL31: 43914 | HM31: 1.08 | HN31: Quarter | HO31: Regular Cash | HQ31: 43907 | HR31: 43924 | HS31: 43927 | HT31: 43951 | HU31: 0.9 | HV31: Quarter | HW31: Regular Cash | HY31: 44027 | HZ31: 44042 | IA31: 44043 | IB31: 44057 | IC31: 0.7 | ID31: Quarter | IE31: Regular Cash | IG31: 43859 | IH31: 43871 | II31: 43872 | IJ31: 43900 | IK31: 0.87 | IL31: Quarter | IM31: Regular Cash
A32: 43818 | B32: 43819 | C32: 43822 | D32: 43861 | E32: 1.569992 | F32: Quarter | G32: Income | I32: 43910 | J32: 43913 | K32: 43914 | L32: 43951 | M32: 0.36269 | N32: Quarter | O32: Income | Q32: 43910 | R32: 43913 | S32: 43914 | T32: 43916 | U32: 0.185741 | V32: Quarter | W32: Income | AG32: 43858 | AH32: 43868 | AI32: 43871 | AJ32: 43874 | AK32: 0.1925 | AL32: Quarter | AM32: Regular Cash | BM32: 43803 | BN32: 43880 | BO32: 43881 | BP32: 43902 | BQ32: 0.51 | BR32: Quarter | BS32: Regular Cash | CC32: 43973 | CD32: 43986 | CE32: 43987 | CF32: 44008 | CG32: 0.004 | CH32: Quarter | CI32: Regular Cash | DA32: 43783 | DB32: 43909 | DC32: 43910 | DD32: 43937 | DE32: 0.328444 | DF32: Quarter | DG32: Regular Cash | DI32: 43902 | DJ32: 43910 | DK32: 43913 | DL32: 43921 | DM32: 0.325 | DN32: Quarter | DO32: Regular Cash | FU32: 43811 | FV32: 43838 | FW32: 43839 | FX32: 43853 | FY32: 0.24 | FZ32: Quarter | GA32: Regular Cash | HA32: 43759 | HB32: 43783 | HC32: 43784 | HD32: 43809 | HE32: 0.645 | HF32: Quarter | HG32: Regular Cash | HI32: 43777 | HJ32: 43805 | HK32: 43808 | HL32: 43816 | HM32: 1.08 | HN32: Quarter | HO32: Regular Cash | HQ32: 43809 | HR32: 43833 | HS32: 43836 | HT32: 43861 | HU32: 0.9 | HV32: Quarter | HW32: Regular Cash | HY32: 43936 | HZ32: 43951 | IA32: 43952 | IB32: 43966 | IC32: 0.7 | ID32: Quarter | IE32: Regular Cash | IG32: 43768 | IH32: 43777 | II32: 43781 | IJ32: 43809 | IK32: 0.87 | IL32: Quarter | IM32: Regular Cash
A33: 43727 | B33: 43728 | C33: 43731 | D33: 43769 | E33: 1.383619 | F33: Quarter | G33: Income | I33: 43819 | J33: 43822 | K33: 43823 | L33: 43830 | M33: 0.45765 | N33: Quarter | O33: Income | Q33: 43818 | R33: 43819 | S33: 43822 | T33: 43825 | U33: 0.147333 | V33: Quarter | W33: Income | AG33: 43768 | AH33: 43776 | AI33: 43780 | AJ33: 43783 | AK33: 0.1925 | AL33: Quarter | AM33: Regular Cash | BM33: 43726 | BN33: 43789 | BO33: 43790 | BP33: 43811 | BQ33: 0.51 | BR33: Quarter | BS33: Regular Cash | CC33: 43874 | CD33: 43888 | CE33: 43889 | CF33: 43910 | CG33: 0.004 | CH33: Quarter | CI33: Regular Cash | DA33: 43693 | DB33: 43818 | DC33: 43819 | DD33: 43846 | DE33: 0.329342 | DF33: Quarter | DG33: Regular Cash | DI33: 43811 | DJ33: 43819 | DK33: 43822 | DL33: 43830 | DM33: 0.325 | DN33: Quarter | DO33: Regular Cash | FU33: 43719 | FV33: 43747 | FW33: 43748 | FX33: 43762 | FY33: 0.24 | FZ33: Quarter | GA33: Regular Cash | HA33: 43635 | HB33: 43691 | HC33: 43692 | HD33: 43718 | HE33: 0.645 | HF33: Quarter | HG33: Regular Cash | HI33: 43691 | HJ33: 43721 | HK33: 43724 | HL33: 43732 | HM33: 1.08 | HN33: Quarter | HO33: Regular Cash | HQ33: 43725 | HR33: 43741 | HS33: 43742 | HT33: 43769 | HU33: 0.9 | HV33: Quarter | HW33: Regular Cash | HY33: 43853 | HZ33: 43867 | IA33: 43868 | IB33: 43882 | IC33: 0.65 | ID33: Quarter | IE33: Regular Cash | IG33: 43677 | IH33: 43689 | II33: 43690 | IJ33: 43718 | IK33: 0.87 | IL33: Quarter | IM33: Regular Cash
A34: 43636 | B34: 43637 | C34: 43640 | D34: 43677 | E34: 1.43164 | F34: Quarter | G34: Income | I34: 43728 | J34: 43731 | K34: 43732 | L34: 43769 | M34: 0.38415 | N34: Quarter | O34: Income | Q34: 43727 | R34: 43728 | S34: 43731 | T34: 43733 | U34: 0.126352 | V34: Quarter | W34: Income | AG34: 43676 | AH34: 43686 | AI34: 43689 | AJ34: 43692 | AK34: 0.1925 | AL34: Quarter | AM34: Regular Cash | BM34: 43628 | BN34: 43691 | BO34: 43692 | BP34: 43720 | BQ34: 0.46 | BR34: Quarter | BS34: Regular Cash | CC34: 43783 | CD34: 43796 | CE34: 43798 | CF34: 43819 | CG34: 0.004 | CH34: Quarter | CI34: Regular Cash | DA34: 43685 | DB34: 43727 | DC34: 43728 | DD34: 43755 | DE34: 0.2561608 | DF34: Quarter | DG34: Regular Cash | DI34: 43720 | DJ34: 43728 | DK34: 43731 | DL34: 43739 | DM34: 0.265 | DN34: Quarter | DO34: Regular Cash | FU34: 43635 | FV34: 43662 | FW34: 43663 | FX34: 43677 | FY34: 0.24 | FZ34: Quarter | GA34: Regular Cash | HA34: 43591 | HB34: 43601 | HC34: 43602 | HD34: 43626 | HE34: 0.645 | HF34: Quarter | HG34: Regular Cash | HI34: 43621 | HJ34: 43630 | HK34: 43633 | HL34: 43641 | HM34: 1.08 | HN34: Quarter | HO34: Regular Cash | HQ34: 43606 | HR34: 43649 | HS34: 43651 | HT34: 43677 | HU34: 0.8 | HV34: Quarter | HW34: Regular Cash | HY34: 43756 | HZ34: 43769 | IA34: 43770 | IB34: 43784 | IC34: 0.65 | ID34: Quarter | IE34: Regular Cash | IG34: 43579 | IH34: 43595 | II34: 43598 | IJ34: 43626 | IK34: 0.87 | IL34: Quarter | IM34: Regular Cash
A35: 43538 | B35: 43539 | C35: 43542 | D35: 43585 | E35: 1.233119 | F35: Quarter | G35: Income | I35: 43637 | J35: 43640 | K35: 43641 | L35: 43677 | M35: 0.41558 | N35: Quarter | O35: Income | Q35: 43636 | R35: 43637 | S35: 43640 | T35: 43642 | U35: 0.139154 | V35: Quarter | W35: Income | AG35: 43585 | AH35: 43595 | AI35: 43598 | AJ35: 43601 | AK35: 0.1925 | AL35: Quarter | AM35: Regular Cash | BM35: 43535 | BN35: 43600 | BO35: 43601 | BP35: 43629 | BQ35: 0.46 | BR35: Quarter | BS35: Regular Cash | CC35: 43692 | CD35: 43705 | CE35: 43706 | CF35: 43728 | CG35: 0.004 | CH35: Quarter | CI35: Regular Cash | DA35: 43628 | DB35: 43640 | DC35: 43641 | DD35: 43664 | DE35: 1.018074 | DF35: Annual | DG35: Regular Cash | DI35: 43629 | DJ35: 43637 | DK35: 43640 | DL35: 43648 | DM35: 0.265 | DN35: Quarter | DO35: Regular Cash | FU35: 43538 | FV35: 43565 | FW35: 43566 | FX35: 43580 | FY35: 0.24 | FZ35: Quarter | GA35: Regular Cash | HA35: 43305 | HB35: 43535 | HC35: #N/A N/A | HD35: #N/A N/A | HE35: 4.5121 | HF35: None | HG35: Split-Off | HI35: 43523 | HJ35: 43532 | HK35: 43535 | HL35: 43543 | HM35: 0.9 | HN35: Quarter | HO35: Regular Cash | HQ35: 43543 | HR35: 43559 | HS35: 43560 | HT35: 43585 | HU35: 0.8 | HV35: Quarter | HW35: Regular Cash | HY35: 43690 | HZ35: 43706 | IA35: 43707 | IB35: 43721 | IC35: 0.65 | ID35: Quarter | IE35: Regular Cash | IG35: 43495 | IH35: 43504 | II35: 43507 | IJ35: 43535 | IK35: 0.82 | IL35: Quarter | IM35: Regular Cash
A36: 43454 | B36: 43455 | C36: 43458 | D36: 43496 | E36: 1.435429 | F36: Quarter | G36: Income | I36: 43539 | J36: 43542 | K36: 43543 | L36: 43585 | M36: 0.32421 | N36: Quarter | O36: Income | Q36: 43538 | R36: 43539 | S36: 43542 | T36: 43544 | U36: 0.116691 | V36: Quarter | W36: Income | AG36: 43494 | AH36: 43504 | AI36: 43507 | AJ36: 43510 | AK36: 0.1825 | AL36: Quarter | AM36: Regular Cash | BM36: 43432 | BN36: 43516 | BO36: 43517 | BP36: 43538 | BQ36: 0.46 | BR36: Quarter | BS36: Regular Cash | CC36: 43601 | CD36: 43615 | CE36: 43616 | CF36: 43637 | CG36: 0.004 | CH36: Quarter | CI36: Regular Cash | DA36: 43264 | DB36: 43276 | DC36: 43277 | DD36: 43300 | DE36: 1.0357599 | DF36: Annual | DG36: Regular Cash | DI36: 43538 | DJ36: 43544 | DK36: 43545 | DL36: 43553 | DM36: 0.265 | DN36: Quarter | DO36: Regular Cash | FU36: 43451 | FV36: 43480 | FW36: 43481 | FX36: 43495 | FY36: 0.19 | FZ36: Quarter | GA36: Regular Cash | HA36: 43453 | HB36: 43510 | HC36: 43511 | HD36: 43532 | HE36: 0.645 | HF36: Quarter | HG36: Regular Cash | HI36: 43413 | HJ36: 43434 | HK36: 43437 | HL36: 43447 | HM36: 0.9 | HN36: Quarter | HO36: Regular Cash | HQ36: 43445 | HR36: 43468 | HS36: 43469 | HT36: 43496 | HU36: 0.8 | HV36: Quarter | HW36: Regular Cash | HY36: 43581 | HZ36: 43594 | IA36: 43595 | IB36: 43609 | IC36: 0.65 | ID36: Quarter | IE36: Regular Cash | IG36: 43404 | IH36: 43413 | II36: 43417 | IJ36: 43444 | IK36: 0.82 | IL36: Quarter | IM36: Regular Cash
A37: 43363 | B37: 43364 | C37: 43367 | D37: 43404 | E37: 1.322611 | F37: Quarter | G37: Income | I37: 43455 | J37: 43458 | K37: 43460 | L37: 43465 | M37: 0.42061 | N37: Quarter | O37: Income | Q37: 43454 | R37: 43455 | S37: 43458 | T37: 43461 | U37: 0.132547 | V37: Quarter | W37: Income | AG37: 43405 | AH37: 43412 | AI37: 43416 | AJ37: 43419 | AK37: 0.1825 | AL37: Quarter | AM37: Regular Cash | BM37: 43361 | BN37: 43418 | BO37: 43419 | BP37: 43447 | BQ37: 0.46 | BR37: Quarter | BS37: Regular Cash | CC37: 43510 | CD37: 43524 | CE37: 43525 | CF37: 43546 | CG37: 0.004 | CH37: Quarter | CI37: Regular Cash | DA37: 42901 | DB37: 42912 | DC37: 42914 | DD37: 42936 | DE37: 0.920992 | DF37: Annual | DG37: Regular Cash | DI37: 43440 | DJ37: 43452 | DK37: 43453 | DL37: 43462 | DM37: 0.265 | DN37: Quarter | DO37: Regular Cash | FU37: 43360 | FV37: 43388 | FW37: 43389 | FX37: 43403 | FY37: 0.19 | FZ37: Quarter | GA37: Regular Cash | HA37: 43388 | HB37: 43418 | HC37: 43419 | HD37: 43444 | HE37: 0.5625 | HF37: Quarter | HG37: Regular Cash | HI37: 43320 | HJ37: 43349 | HK37: 43350 | HL37: 43361 | HM37: 0.9 | HN37: Quarter | HO37: Regular Cash | HQ37: 43361 | HR37: 43377 | HS37: 43378 | HT37: 43404 | HU37: 0.8 | HV37: Quarter | HW37: Regular Cash | HY37: 43489 | HZ37: 43503 | IA37: 43504 | IB37: 43518 | IC37: 0.57 | ID37: Quarter | IE37: Regular Cash | IG37: 43306 | IH37: 43322 | II37: 43325 | IJ37: 43353 | IK37: 0.82 | IL37: Quarter | IM37: Regular Cash
A38: 43265 | B38: 43266 | C38: 43269 | D38: 43312 | E38: 1.245568 | F38: Quarter | G38: Income | I38: 43364 | J38: 43367 | K38: 43368 | L38: 43404 | M38: 0.32975 | N38: Quarter | O38: Income | Q38: 43363 | R38: 43364 | S38: 43367 | T38: 43369 | U38: 0.127185 | V38: Quarter | W38: Income | AG38: 43312 | AH38: 43322 | AI38: 43325 | AJ38: 43328 | AK38: 0.1825 | AL38: Quarter | AM38: Regular Cash | BM38: 43264 | BN38: 43327 | BO38: 43328 | BP38: 43356 | BQ38: 0.42 | BR38: Quarter | BS38: Regular Cash | CC38: 43419 | CD38: 43433 | CE38: 43434 | CF38: 43455 | CG38: 0.004 | CH38: Quarter | CI38: Regular Cash | DA38: 42531 | DB38: 42548 | DC38: 42550 | DD38: 42572 | DE38: 0.75155 | DF38: Annual | DG38: Regular Cash | DI38: 43349 | DJ38: 43361 | DK38: 43362 | DL38: 43371 | DM38: 0.175 | DN38: Quarter | DO38: Regular Cash | FU38: 43270 | FV38: 43297 | FW38: 43298 | FX38: 43312 | FY38: 0.19 | FZ38: Quarter | GA38: Regular Cash | HA38: 43269 | HB38: 43326 | HC38: 43327 | HD38: 43353 | HE38: 0.5625 | HF38: Quarter | HG38: Regular Cash | HI38: 43257 | HJ38: 43266 | HK38: 43269 | HL38: 43277 | HM38: 0.9 | HN38: Quarter | HO38: Regular Cash | HQ38: 43235 | HR38: 43286 | HS38: 43287 | HT38: 43312 | HU38: 0.56 | HV38: Quarter | HW38: Regular Cash | HY38: 43397 | HZ38: 43412 | IA38: 43413 | IB38: 43427 | IC38: 0.57 | ID38: Quarter | IE38: Regular Cash | IG38: 43215 | IH38: 43231 | II38: 43234 | IJ38: 43262 | IK38: 0.82 | IL38: Quarter | IM38: Regular Cash
A39: 43174 | B39: 43175 | C39: 43178 | D39: 43220 | E39: 1.096775 | F39: Quarter | G39: Income | I39: 43266 | J39: 43269 | K39: 43270 | L39: 43312 | M39: 0.37837 | N39: Quarter | O39: Income | Q39: 43265 | R39: 43266 | S39: 43269 | T39: 43271 | U39: 0.127637 | V39: Quarter | W39: Income | AG39: 43221 | AH39: 43231 | AI39: 43234 | AJ39: 43237 | AK39: 0.1825 | AL39: Quarter | AM39: Regular Cash | BM39: 43171 | BN39: 43236 | BO39: 43237 | BP39: 43265 | BQ39: 0.42 | BR39: Quarter | BS39: Regular Cash | CC39: 43328 | CD39: 43341 | CE39: 43342 | CF39: 43364 | CG39: 0.00375 | CH39: Quarter | CI39: Regular Cash | DA39: 42173 | DB39: 42184 | DC39: 42186 | DD39: 42208 | DE39: 0.5782786 | DF39: Annual | DG39: Regular Cash | DI39: 43258 | DJ39: 43270 | DK39: 43271 | DL39: 43280 | DM39: 0.175 | DN39: Quarter | DO39: Regular Cash | FU39: 43178 | FV39: 43206 | FW39: 43207 | FX39: 43221 | FY39: 0.19 | FZ39: Quarter | GA39: Regular Cash | HA39: 43227 | HB39: 43236 | HC39: 43237 | HD39: 43259 | HE39: 0.5625 | HF39: Quarter | HG39: Regular Cash | HI39: 43145 | HJ39: 43167 | HK39: 43168 | HL39: 43179 | HM39: 0.75 | HN39: Quarter | HO39: Regular Cash | HQ39: 43179 | HR39: 43195 | HS39: 43196 | HT39: 43220 | HU39: 0.56 | HV39: Quarter | HW39: Regular Cash | HY39: 43329 | HZ39: 43342 | IA39: 43343 | IB39: 43357 | IC39: 0.57 | ID39: Quarter | IE39: Regular Cash | IG39: 43131 | IH39: 43140 | II39: 43143 | IJ39: 43168 | IK39: 0.77 | IL39: Quarter | IM39: Regular Cash
A40: 43083 | B40: 43084 | C40: 43087 | D40: 43131 | E40: 1.351333 | F40: Quarter | G40: Income | I40: 43175 | J40: 43178 | K40: 43179 | L40: 43220 | M40: 0.27655 | N40: Quarter | O40: Income | Q40: 43174 | R40: 43175 | S40: 43178 | T40: 43180 | U40: 0.108874 | V40: Quarter | W40: Income | AG40: 43132 | AH40: 43140 | AI40: 43143 | AJ40: 43146 | AK40: 0.1575 | AL40: Quarter | AM40: Regular Cash | BM40: 43068 | BN40: 43145 | BO40: 43146 | BP40: 43167 | BQ40: 0.42 | BR40: Quarter | BS40: Regular Cash | CC40: 43230 | CD40: 43243 | CE40: 43244 | CF40: 43266 | CG40: 0.00375 | CH40: Quarter | CI40: Regular Cash | DA40: 41817 | DB40: 41834 | DC40: 41836 | DD40: 41857 | DE40: 0.3995621 | DF40: Annual | DG40: Regular Cash | DI40: 43174 | DJ40: 43180 | DK40: 43181 | DL40: 43188 | DM40: 0.175 | DN40: Quarter | DO40: Regular Cash | FU40: 43083 | FV40: 43109 | FW40: 43110 | FX40: 43124 | FY40: 0.19 | FZ40: Quarter | GA40: Regular Cash | HA40: 43080 | HB40: 43145 | HC40: 43146 | HD40: 43168 | HE40: 0.5625 | HF40: Quarter | HG40: Regular Cash | HI40: 43047 | HJ40: 43069 | HK40: 43070 | HL40: 43081 | HM40: 0.75 | HN40: Quarter | HO40: Regular Cash | HQ40: 43081 | HR40: 43104 | HS40: 43105 | HT40: 43131 | HU40: 0.56 | HV40: Quarter | HW40: Regular Cash | HY40: 43214 | HZ40: 43230 | IA40: 43231 | IB40: 43245 | IC40: 0.57 | ID40: Quarter | IE40: Regular Cash | IG40: 43033 | IH40: 43049 | II40: 43052 | IJ40: 43080 | IK40: 0.77 | IL40: Quarter | IM40: Regular Cash
A41: 42992 | B41: 42993 | C41: 42996 | D41: 43039 | E41: 1.234574 | F41: Quarter | G41: Income | I41: 43084 | J41: 43087 | K41: 43088 | L41: 43098 | M41: 0.32941 | N41: Quarter | O41: Income | Q41: 43083 | R41: 43084 | S41: 43087 | T41: 43095 | U41: 0.119127 | V41: Quarter | W41: Income | AG41: 43041 | AH41: 43049 | AI41: 43052 | AJ41: 43055 | AK41: 0.1575 | AL41: Quarter | AM41: Regular Cash | BM41: 42997 | BN41: 43054 | BO41: 43055 | BP41: 43083 | BQ41: 0.42 | BR41: Quarter | BS41: Regular Cash | CC41: 43139 | CD41: 43153 | CE41: 43154 | CF41: 43175 | CG41: 0.00375 | CH41: Quarter | CI41: Regular Cash | DA41: 41443 | DB41: 41458 | DC41: 41463 | DD41: 41484 | DE41: 0.400866 | DF41: Annual | DG41: Regular Cash | DI41: 43075 | DJ41: 43087 | DK41: 43088 | DL41: 43098 | DM41: 0.175 | DN41: Quarter | DO41: Regular Cash | FU41: 42992 | FV41: 43018 | FW41: 43019 | FX41: 43033 | FY41: 0.19 | FZ41: Quarter | GA41: Regular Cash | HA41: 43024 | HB41: 43053 | HC41: 43054 | HD41: 43077 | HE41: 0.52 | HF41: Quarter | HG41: Regular Cash | HI41: 42963 | HJ41: 42985 | HK41: 42986 | HL41: 42997 | HM41: 0.75 | HN41: Quarter | HO41: Regular Cash | HQ41: 42997 | HR41: 43013 | HS41: 43014 | HT41: 43039 | HU41: 0.56 | HV41: Quarter | HW41: Regular Cash | HY41: 43130 | HZ41: 43146 | IA41: 43147 | IB41: 43161 | IC41: 0.5 | ID41: Quarter | IE41: Regular Cash | IG41: 42942 | IH41: 42957 | II41: 42961 | IJ41: 42989 | IK41: 0.77 | IL41: Quarter | IM41: Regular Cash
A42: 42901 | B42: 42902 | C42: 42906 | D42: 42947 | E42: 1.183108 | F42: Quarter | G42: Income | I42: 42993 | J42: 42996 | K42: 42997 | L42: 43039 | M42: 0.31938 | N42: Quarter | O42: Income | Q42: 42992 | R42: 42993 | S42: 42996 | T42: 43003 | U42: 0.104612 | V42: Quarter | W42: Income | AG42: 42948 | AH42: 42957 | AI42: 42961 | AJ42: 42964 | AK42: 0.1575 | AL42: Quarter | AM42: Regular Cash | BM42: 42899 | BN42: 42962 | BO42: 42964 | BP42: 42992 | BQ42: 0.39 | BR42: Quarter | BS42: Regular Cash | CC42: 43048 | CD42: 43061 | CE42: 43063 | CF42: 43084 | CG42: 0.00375 | CH42: Quarter | CI42: Regular Cash | DA42: 41079 | DB42: 41095 | DC42: 41099 | DD42: 41120 | DE42: 0.3978891 | DF42: Annual | DG42: Regular Cash | DI42: 42976 | DJ42: 42996 | DK42: 42997 | DL42: 43007 | DM42: 0.102 | DN42: Quarter | DO42: Regular Cash | FU42: 42907 | FV42: 42933 | FW42: 42935 | FX42: 42949 | FY42: 0.19 | FZ42: Quarter | GA42: Regular Cash | HA42: 42905 | HB42: 42958 | HC42: 42962 | HD42: 42986 | HE42: 0.52 | HF42: Quarter | HG42: Regular Cash | HI42: 42893 | HJ42: 42901 | HK42: 42905 | HL42: 42913 | HM42: 0.75 | HN42: Quarter | HO42: Regular Cash | HQ42: 42871 | HR42: 42919 | HS42: 42922 | HT42: 42947 | HU42: 0.5 | HV42: Quarter | HW42: Regular Cash | HY42: 43038 | HZ42: 43055 | IA42: 43056 | IB42: 43070 | IC42: 0.5 | ID42: Quarter | IE42: Regular Cash | IG42: 42851 | IH42: 42865 | II42: 42867 | IJ42: 42895 | IK42: 0.77 | IL42: Quarter | IM42: Regular Cash
A43: 42810 | B43: 42811 | C43: 42815 | D43: 42853 | E43: 1.033118 | F43: Quarter | G43: Income | I43: 42901 | J43: 42902 | K43: 42906 | L43: 42947 | M43: 0.37842 | N43: Quarter | O43: Income | Q43: 42901 | R43: 42902 | S43: 42906 | T43: 42912 | U43: 0.11169 | V43: Quarter | W43: Income | AG43: 42857 | AH43: 42866 | AI43: 42870 | AJ43: 42873 | AK43: 0.1575 | AL43: Quarter | AM43: Regular Cash | BM43: 42808 | BN43: 42871 | BO43: 42873 | BP43: 42894 | BQ43: 0.39 | BR43: Quarter | BS43: Regular Cash | CC43: 42957 | CD43: 42969 | CE43: 42971 | CF43: 42996 | CG43: 0.0035 | CH43: Quarter | CI43: Regular Cash | DA43: 40710 | DB43: 40723 | DC43: 40725 | DD43: 40749 | DE43: 0.414619 | DF43: Annual | DG43: Regular Cash | DI43: 42887 | DJ43: 42901 | DK43: 42905 | DL43: 42916 | DM43: 0.102 | DN43: Quarter | DO43: Regular Cash | FU43: 42809 | FV43: 42835 | FW43: 42837 | FX43: 42851 | FY43: 0.19 | FZ43: Quarter | GA43: Regular Cash | HA43: 42856 | HB43: 42866 | HC43: 42870 | HD43: 42895 | HE43: 0.52 | HF43: Quarter | HG43: Regular Cash | HI43: 42775 | HJ43: 42802 | HK43: 42804 | HL43: 42815 | HM43: 0.625 | HN43: Quarter | HO43: Regular Cash | HQ43: 42815 | HR43: 42829 | HS43: 42831 | HT43: 42855 | HU43: 0.5 | HV43: Quarter | HW43: Regular Cash | HY43: 42947 | HZ43: 42963 | IA43: 42965 | IB43: 42979 | IC43: 0.5 | ID43: Quarter | IE43: Regular Cash | IG43: 42760 | IH43: 42774 | II43: 42776 | IJ43: 42804 | IK43: 0.75 | IL43: Quarter | IM43: Regular Cash
A44: 42719 | B44: 42720 | C44: 42724 | D44: 42766 | E44: 1.32893 | F44: Quarter | G44: Income | I44: 42810 | J44: 42811 | K44: 42815 | L44: 42853 | M44: 0.27415 | N44: Quarter | O44: Income | Q44: 42810 | R44: 42811 | S44: 42815 | T44: 42821 | U44: 0.10262 | V44: Quarter | W44: Income | AG44: 42766 | AH44: 42775 | AI44: 42779 | AJ44: 42782 | AK44: 0.1425 | AL44: Quarter | AM44: Regular Cash | BM44: 42704 | BN44: 42780 | BO44: 42782 | BP44: 42803 | BQ44: 0.39 | BR44: Quarter | BS44: Regular Cash | CC44: 42864 | CD44: 42874 | CE44: 42878 | CF44: 42900 | CG44: 0.0035 | CH44: Quarter | CI44: Regular Cash | DA44: 40350 | DB44: 40365 | DC44: 40367 | DD44: 40386 | DE44: 0.3727466 | DF44: Annual | DG44: Regular Cash | DI44: 42795 | DJ44: 42810 | DK44: 42814 | DL44: 42825 | DM44: 0.102 | DN44: Quarter | DO44: Regular Cash | FU44: 42719 | FV44: 42738 | FW44: 42740 | FX44: 42761 | FY44: 0.15 | FZ44: Quarter | GA44: Regular Cash | HA44: 42716 | HB44: 42779 | HC44: 42781 | HD44: 42804 | HE44: 0.52 | HF44: Quarter | HG44: Regular Cash | HI44: 42683 | HJ44: 42704 | HK44: 42706 | HL44: 42717 | HM44: 0.625 | HN44: Quarter | HO44: Regular Cash | HQ44: 42717 | HR44: 42739 | HS44: 42741 | HT44: 42766 | HU44: 0.48 | HV44: Quarter | HW44: Regular Cash | HY44: 42850 | HZ44: 42865 | IA44: 42867 | IB44: 42881 | IC44: 0.5 | ID44: Quarter | IE44: Regular Cash | IG44: 42669 | IH44: 42682 | II44: 42684 | IJ44: 42713 | IK44: 0.75 | IL44: Quarter | IM44: Regular Cash
A45: 42628 | B45: 42629 | C45: 42633 | D45: 42674 | E45: 1.082068 | F45: Quarter | G45: Income | I45: 42719 | J45: 42720 | K45: 42724 | L45: 42734 | M45: 0.35494 | N45: Quarter | O45: Income | Q45: 42719 | R45: 42720 | S45: 42724 | T45: 42731 | U45: 0.108116 | V45: Quarter | W45: Income | AG45: 42668 | AH45: 42677 | AI45: 42681 | AJ45: 42684 | AK45: 0.1425 | AL45: Quarter | AM45: Regular Cash | BM45: 42633 | BN45: 42689 | BO45: 42691 | BP45: 42712 | BQ45: 0.39 | BR45: Quarter | BS45: Regular Cash | CC45: 42775 | CD45: 42788 | CE45: 42790 | CF45: 42811 | CG45: 0.0035 | CH45: Quarter | CI45: Regular Cash | DI45: 42712 | DJ45: 42718 | DK45: 42720 | DL45: 42734 | DM45: 0.102 | DN45: Quarter | DO45: Regular Cash | FU45: 42628 | FV45: 42650 | FW45: 42655 | FX45: 42669 | FY45: 0.15 | FZ45: Quarter | GA45: Regular Cash | HA45: 42660 | HB45: 42684 | HC45: 42689 | HD45: 42713 | HE45: 0.51 | HF45: Quarter | HG45: Regular Cash | HI45: 42585 | HJ45: 42620 | HK45: 42622 | HL45: 42633 | HM45: 0.625 | HN45: Quarter | HO45: Regular Cash | HQ45: 42633 | HR45: 42647 | HS45: 42649 | HT45: 42674 | HU45: 0.48 | HV45: Quarter | HW45: Regular Cash | HY45: 42850 | HZ45: 42863 | IA45: 42865 | IB45: 42881 | IC45: 7 | ID45: None | IE45: Special Cash | IG45: 42578 | IH45: 42592 | II45: 42594 | IJ45: 42622 | IK45: 0.75 | IL45: Quarter | IM45: Regular Cash
A46: 42537 | B46: 42538 | C46: 42542 | D46: 42580 | E46: 1.078442 | F46: Quarter | G46: Income | I46: 42628 | J46: 42629 | K46: 42633 | L46: 42674 | M46: 0.29387 | N46: Quarter | O46: Income | Q46: 42628 | R46: 42629 | S46: 42633 | T46: 42639 | U46: 0.097786 | V46: Quarter | W46: Income | AG46: 42577 | AH46: 42586 | AI46: 42590 | AJ46: 42593 | AK46: 0.1425 | AL46: Quarter | AM46: Regular Cash | BM46: 42535 | BN46: 42598 | BO46: 42600 | BP46: 42621 | BQ46: 0.36 | BR46: Quarter | BS46: Regular Cash | CC46: 42684 | CD46: 42697 | CE46: 42702 | CF46: 42723 | CG46: 0.0035 | CH46: Quarter | CI46: Regular Cash | DI46: 42614 | DJ46: 42628 | DK46: 42632 | DL46: 42643 | DM46: 0.051 | DN46: Quarter | DO46: Regular Cash | FU46: 42537 | FV46: 42552 | FW46: 42557 | FX46: 42578 | FY46: 0.15 | FZ46: Quarter | GA46: Regular Cash | HA46: 42541 | HB46: 42593 | HC46: 42597 | HD46: 42622 | HE46: 0.51 | HF46: Quarter | HG46: Regular Cash | HI46: 42529 | HJ46: 42536 | HK46: 42538 | HL46: 42549 | HM46: 0.625 | HN46: Quarter | HO46: Regular Cash | HQ46: 42507 | HR46: 42552 | HS46: 42557 | HT46: 42582 | HU46: 0.48 | HV46: Quarter | HW46: Regular Cash | HY46: 42762 | HZ46: 42774 | IA46: 42776 | IB46: 42790 | IC46: 0.45 | ID46: Quarter | IE46: Regular Cash | IG46: 42487 | IH46: 42501 | II46: 42503 | IJ46: 42531 | IK46: 0.75 | IL46: Quarter | IM46: Regular Cash
A47: 42446 | B47: 42447 | C47: 42451 | D47: 42489 | E47: 1.049604 | F47: Quarter | G47: Income | I47: 42537 | J47: 42538 | K47: 42542 | L47: 42580 | M47: 0.28665 | N47: Quarter | O47: Income | Q47: 42537 | R47: 42538 | S47: 42542 | T47: 42548 | U47: 0.105655 | V47: Quarter | W47: Income | AG47: 42486 | AH47: 42495 | AI47: 42499 | AJ47: 42502 | AK47: 0.1425 | AL47: Quarter | AM47: Regular Cash | BM47: 42444 | BN47: 42507 | BO47: 42509 | BP47: 42530 | BQ47: 0.36 | BR47: Quarter | BS47: Regular Cash | CC47: 42593 | CD47: 42605 | CE47: 42607 | CF47: 42629 | CG47: 0.002875 | CH47: Quarter | CI47: Regular Cash | DI47: 42523 | DJ47: 42536 | DK47: 42538 | DL47: 42551 | DM47: 0.05 | DN47: Quarter | DO47: Regular Cash | FU47: 42444 | FV47: 42472 | FW47: 42474 | FX47: 42488 | FY47: 0.15 | FZ47: Quarter | GA47: Regular Cash | HA47: 42492 | HB47: 42501 | HC47: 42503 | HD47: 42531 | HE47: 0.51 | HF47: Quarter | HG47: Regular Cash | HI47: 42409 | HJ47: 42438 | HK47: 42440 | HL47: 42451 | HM47: 0.5 | HN47: Quarter | HO47: Regular Cash | HQ47: 42444 | HR47: 42464 | HS47: 42466 | HT47: 42490 | HU47: 0.44 | HV47: Quarter | HW47: Regular Cash | HY47: 42655 | HZ47: 42676 | IA47: 42678 | IB47: 42692 | IC47: 0.45 | ID47: Quarter | IE47: Regular Cash | IG47: 42396 | IH47: 42409 | II47: 42411 | IJ47: 42439 | IK47: 0.73 | IL47: Quarter | IM47: Regular Cash
A48: 42355 | B48: 42356 | C48: 42360 | D48: 42398 | E48: 1.21155 | F48: Quarter | G48: Income | I48: 42446 | J48: 42447 | K48: 42451 | L48: 42489 | M48: 0.3178 | N48: Quarter | O48: Income | Q48: 42446 | R48: 42447 | S48: 42451 | T48: 42458 | U48: 0.110113 | V48: Quarter | W48: Income | AG48: 42395 | AH48: 42404 | AI48: 42408 | AJ48: 42411 | AK48: 0.13 | AL48: Quarter | AM48: Regular Cash | BM48: 42340 | BN48: 42416 | BO48: 42418 | BP48: 42439 | BQ48: 0.36 | BR48: Quarter | BS48: Regular Cash | CC48: 42502 | CD48: 42514 | CE48: 42516 | CF48: 42541 | CG48: 0.002875 | CH48: Quarter | CI48: Regular Cash | DI48: 42432 | DJ48: 42445 | DK48: 42447 | DL48: 42460 | DM48: 0.049 | DN48: Quarter | DO48: Regular Cash | FU48: 42354 | FV48: 42373 | FW48: 42375 | FX48: 42396 | FY48: 0.15 | FZ48: Quarter | GA48: Regular Cash | HA48: 42346 | HB48: 42410 | HC48: 42412 | HD48: 42439 | HE48: 0.51 | HF48: Quarter | HG48: Regular Cash | HI48: 42314 | HJ48: 42340 | HK48: 42342 | HL48: 42353 | HM48: 0.5 | HN48: Quarter | HO48: Regular Cash | HQ48: 42346 | HR48: 42373 | HS48: 42375 | HT48: 42400 | HU48: 0.44 | HV48: Quarter | HW48: Regular Cash | HY48: 42576 | HZ48: 42592 | IA48: 42594 | IB48: 42608 | IC48: 0.45 | ID48: Quarter | IE48: Regular Cash | IG48: 42305 | IH48: 42317 | II48: 42320 | IJ48: 42348 | IK48: 0.73 | IL48: Quarter | IM48: Regular Cash
A49: 42264 | B49: 42265 | C49: 42269 | D49: 42307 | E49: 1.03343 | F49: Quarter | G49: Income | I49: 42355 | J49: 42356 | K49: 42360 | L49: 42369 | M49: 0.34233 | N49: Quarter | O49: Income | Q49: 42355 | R49: 42356 | S49: 42360 | T49: 42367 | U49: 0.107953 | V49: Quarter | W49: Income | AG49: 42304 | AH49: 42313 | AI49: 42317 | AJ49: 42320 | AK49: 0.13 | AL49: Quarter | AM49: Regular Cash | BM49: 42262 | BN49: 42325 | BO49: 42327 | BP49: 42348 | BQ49: 0.36 | BR49: Quarter | BS49: Regular Cash | CC49: 42417 | CD49: 42429 | CE49: 42431 | CF49: 42452 | CG49: 0.002875 | CH49: Quarter | CI49: Regular Cash | DI49: 42346 | DJ49: 42354 | DK49: 42356 | DL49: 42368 | DM49: 0.044 | DN49: Quarter | DO49: Regular Cash | FU49: 42263 | FV49: 42286 | FW49: 42291 | FX49: 42305 | FY49: 0.15 | FZ49: Quarter | GA49: Regular Cash | HA49: 42296 | HB49: 42318 | HC49: 42321 | HD49: 42348 | HE49: 0.5 | HF49: Quarter | HG49: Regular Cash | HI49: 42228 | HJ49: 42256 | HK49: 42258 | HL49: 42269 | HM49: 0.5 | HN49: Quarter | HO49: Regular Cash | HQ49: 42262 | HR49: 42279 | HS49: 42283 | HT49: 42308 | HU49: 0.44 | HV49: Quarter | HW49: Regular Cash | HY49: 42474 | HZ49: 42487 | IA49: 42489 | IB49: 42503 | IC49: 0.45 | ID49: Quarter | IE49: Regular Cash | IG49: 42214 | IH49: 42227 | II49: 42229 | IJ49: 42257 | IK49: 0.73 | IL49: Quarter | IM49: Regular Cash
A50: 42173 | B50: 42174 | C50: 42178 | D50: 42216 | E50: 1.03007 | F50: Quarter | G50: Income | I50: 42264 | J50: 42265 | K50: 42269 | L50: 42307 | M50: 0.26002 | N50: Quarter | O50: Income | Q50: 42264 | R50: 42265 | S50: 42269 | T50: 42275 | U50: 0.091715 | V50: Quarter | W50: Income | AG50: 42206 | AH50: 42222 | AI50: 42226 | AJ50: 42229 | AK50: 0.13 | AL50: Quarter | AM50: Regular Cash | BM50: 42164 | BN50: 42234 | BO50: 42236 | BP50: 42257 | BQ50: 0.31 | BR50: Quarter | BS50: Regular Cash | CC50: 42313 | CD50: 42326 | CE50: 42328 | CF50: 42352 | CG50: 0.002875 | CH50: Quarter | CI50: Regular Cash | DI50: 42250 | DJ50: 42263 | DK50: 42265 | DL50: 42277 | DM50: 0.042 | DN50: Quarter | DO50: Regular Cash | FU50: 42172 | FV50: 42191 | FW50: 42193 | FX50: 42214 | FY50: 0.15 | FZ50: Quarter | GA50: Regular Cash | HA50: 42170 | HB50: 42228 | HC50: 42230 | HD50: 42257 | HE50: 0.5 | HF50: Quarter | HG50: Regular Cash | HI50: 42158 | HJ50: 42166 | HK50: 42170 | HL50: 42179 | HM50: 0.5 | HN50: Quarter | HO50: Regular Cash | HQ50: 42143 | HR50: 42186 | HS50: 42191 | HT50: 42216 | HU50: 0.44 | HV50: Quarter | HW50: Regular Cash | HY50: 42398 | HZ50: 42410 | IA50: 42412 | IB50: 42426 | IC50: 0.4 | ID50: Quarter | IE50: Regular Cash | IG50: 42123 | IH50: 42135 | II50: 42137 | IJ50: 42165 | IK50: 0.73 | IL50: Quarter | IM50: Regular Cash
A51: 42082 | B51: 42083 | C51: 42087 | D51: 42124 | E51: 0.93081 | F51: Quarter | G51: Income | I51: 42173 | J51: 42174 | K51: 42178 | L51: 42216 | M51: 0.25416 | N51: Quarter | O51: Income | Q51: 42173 | R51: 42174 | S51: 42178 | T51: 42184 | U51: 0.096445 | V51: Quarter | W51: Income | AG51: 42121 | AH51: 42131 | AI51: 42135 | AJ51: 42138 | AK51: 0.13 | AL51: Quarter | AM51: Regular Cash | BM51: 42073 | BN51: 42143 | BO51: 42145 | BP51: 42166 | BQ51: 0.31 | BR51: Quarter | BS51: Regular Cash | CC51: 42222 | CD51: 42234 | CE51: 42236 | CF51: 42258 | CG51: 0.002438 | CH51: Quarter | CI51: Regular Cash | DI51: 42159 | DJ51: 42172 | DK51: 42174 | DL51: 42185 | DM51: 0.04 | DN51: Quarter | DO51: Regular Cash | FU51: 42080 | FV51: 42096 | FW51: 42101 | FX51: 42122 | FY51: 0.15 | FZ51: Quarter | GA51: Regular Cash | HA51: 42128 | HB51: 42138 | HC51: 42142 | HD51: 42165 | HE51: 0.5 | HF51: Quarter | HG51: Regular Cash | HI51: 42045 | HJ51: 42074 | HK51: 42076 | HL51: 42087 | HM51: 0.375 | HN51: Quarter | HO51: Regular Cash | HQ51: 42080 | HR51: 42095 | HS51: 42100 | HT51: 42124 | HU51: 0.4 | HV51: Quarter | HW51: Regular Cash | HY51: 42306 | HZ51: 42318 | IA51: 42321 | IB51: 42335 | IC51: 0.4 | ID51: Quarter | IE51: Regular Cash | IG51: 42032 | IH51: 42041 | II51: 42045 | IJ51: 42073 | IK51: 0.69 | IL51: Quarter | IM51: Regular Cash
A52: 41991 | B52: 41992 | C52: 41996 | D52: 42034 | E52: 1.13492 | F52: Quarter | G52: Income | I52: 42082 | J52: 42083 | K52: 42087 | L52: 42124 | M52: 0.24806 | N52: Quarter | O52: Income | Q52: 42082 | R52: 42083 | S52: 42087 | T52: 42093 | U52: 0.086715 | V52: Quarter | W52: Income | AG52: 42031 | AH52: 42040 | AI52: 42044 | AJ52: 42047 | AK52: 0.1175 | AL52: Quarter | AM52: Regular Cash | BM52: 41976 | BN52: 42052 | BO52: 42054 | BP52: 42075 | BQ52: 0.31 | BR52: Quarter | BS52: Regular Cash | CC52: 42131 | CD52: 42143 | CE52: 42145 | CF52: 42167 | CG52: 0.002438 | CH52: Quarter | CI52: Regular Cash | DI52: 42068 | DJ52: 42081 | DK52: 42083 | DL52: 42094 | DM52: 0.038 | DN52: Quarter | DO52: Regular Cash | FU52: 41990 | FV52: 42009 | FW52: 42011 | FX52: 42032 | FY52: 0.12 | FZ52: Quarter | GA52: Regular Cash | HA52: 41988 | HB52: 42046 | HC52: 42048 | HD52: 42073 | HE52: 0.5 | HF52: Quarter | HG52: Regular Cash | HI52: 41949 | HJ52: 41976 | HK52: 41978 | HL52: 41989 | HM52: 0.375 | HN52: Quarter | HO52: Regular Cash | HQ52: 41982 | HR52: 42006 | HS52: 42010 | HT52: 42035 | HU52: 0.4 | HV52: Quarter | HW52: Regular Cash | HY52: 42212 | HZ52: 42228 | IA52: 42230 | IB52: 42244 | IC52: 0.4 | ID52: Quarter | IE52: Regular Cash | IG52: 41941 | IH52: 41950 | II52: 41955 | IJ52: 41983 | IK52: 0.69 | IL52: Quarter | IM52: Regular Cash
A53: 41900 | B53: 41901 | C53: 41905 | D53: 41943 | E53: 0.93919 | F53: Quarter | G53: Income | I53: 41991 | J53: 41992 | K53: 41996 | L53: 42004 | M53: 0.38681 | N53: Quarter | O53: Income | Q53: 41991 | R53: 41992 | S53: 41996 | T53: 42003 | U53: 0.108245 | V53: Quarter | W53: Income | AG53: 41932 | AH53: 41949 | AI53: 41953 | AJ53: 41956 | AK53: 0.1175 | AL53: Quarter | AM53: Regular Cash | BM53: 41898 | BN53: 41961 | BO53: 41963 | BP53: 41984 | BQ53: 0.31 | BR53: Quarter | BS53: Regular Cash | CC53: 42046 | CD53: 42059 | CE53: 42061 | CF53: 42082 | CG53: 0.002125 | CH53: Quarter | CI53: Regular Cash | DI53: 41982 | DJ53: 41990 | DK53: 41992 | DL53: 42004 | DM53: 0.035 | DN53: Quarter | DO53: Regular Cash | FU53: 41900 | FV53: 41918 | FW53: 41920 | FX53: 41941 | FY53: 0.12 | FZ53: Quarter | GA53: Regular Cash | HA53: 41932 | HB53: 41955 | HC53: 41957 | HD53: 41983 | HE53: 0.49 | HF53: Quarter | HG53: Regular Cash | HI53: 41863 | HJ53: 41892 | HK53: 41894 | HL53: 41905 | HM53: 0.375 | HN53: Quarter | HO53: Regular Cash | HQ53: 41898 | HR53: 41914 | HS53: 41918 | HT53: 41943 | HU53: 0.4 | HV53: Quarter | HW53: Regular Cash | HY53: 42111 | HZ53: 42123 | IA53: 42125 | IB53: 42139 | IC53: 0.4 | ID53: Quarter | IE53: Regular Cash | IG53: 41850 | IH53: 41862 | II53: 41864 | IJ53: 41892 | IK53: 0.69 | IL53: Quarter | IM53: Regular Cash
A54: 41809 | B54: 41810 | C54: 41814 | D54: 41851 | E54: 0.93669 | F54: Quarter | G54: Income | I54: 41900 | J54: 41901 | K54: 41905 | L54: 41943 | M54: 0.2378 | N54: Quarter | O54: Income | Q54: 41900 | R54: 41901 | S54: 41905 | T54: 41911 | U54: 0.08688 | V54: Quarter | W54: Income | AG54: 41842 | AH54: 41858 | AI54: 41862 | AJ54: 41865 | AK54: 0.1175 | AL54: Quarter | AM54: Regular Cash | BM54: 41800 | BN54: 41870 | BO54: 41872 | BP54: 41893 | BQ54: 0.28 | BR54: Quarter | BS54: Regular Cash | CC54: 41949 | CD54: 41962 | CE54: 41964 | CF54: 41988 | CG54: 0.002125 | CH54: Quarter | CI54: Regular Cash | DI54: 41886 | DJ54: 41899 | DK54: 41901 | DL54: 41912 | DM54: 0.032 | DN54: Quarter | DO54: Regular Cash | FU54: 41809 | FV54: 41827 | FW54: 41829 | FX54: 41850 | FY54: 0.12 | FZ54: Quarter | GA54: Regular Cash | HA54: 41806 | HB54: 41864 | HC54: 41866 | HD54: 41892 | HE54: 0.49 | HF54: Quarter | HG54: Regular Cash | HI54: 41794 | HJ54: 41802 | HK54: 41806 | HL54: 41815 | HM54: 0.375 | HN54: Quarter | HO54: Regular Cash | HQ54: 41724 | HR54: 41821 | HS54: 41823 | HT54: 41851 | HU54: 0.4 | HV54: Quarter | HW54: Regular Cash | HY54: 42033 | HZ54: 42046 | IA54: 42048 | IB54: 42062 | IC54: 0.355 | ID54: Quarter | IE54: Regular Cash | IG54: 41759 | IH54: 41768 | II54: 41772 | IJ54: 41800 | IK54: 0.69 | IL54: Quarter | IM54: Regular Cash
A55: 41718 | B55: 41719 | C55: 41723 | D55: 41759 | E55: 0.82461 | F55: Quarter | G55: Income | I55: 41652 | J55: 41810 | K55: 41814 | L55: 41851 | M55: 0.2491 | N55: Quarter | O55: Income | Q55: 41809 | R55: 41810 | S55: 41814 | T55: 41820 | U55: 0.08801 | V55: Quarter | W55: Income | AG55: 41752 | AH55: 41799 | AI55: 41792 | AJ55: 41796 | AK55: 7 | AL55: None | AM55: Stock Split | BM55: 41709 | BN55: 41772 | BO55: 41774 | BP55: 41802 | BQ55: 0.28 | BR55: Quarter | BS55: Regular Cash | CC55: 41858 | CD55: 41870 | CE55: 41872 | CF55: 41894 | CG55: 0.002125 | CH55: Quarter | CI55: Regular Cash | DI55: 41795 | DJ55: 41807 | DK55: 41809 | DL55: 41820 | DM55: 0.029 | DN55: Quarter | DO55: Regular Cash | FU55: 41716 | FV55: 41733 | FW55: 41737 | FX55: 41758 | FY55: 0.12 | FZ55: Quarter | GA55: Regular Cash | HA55: 41764 | HB55: 41772 | HC55: 41774 | HD55: 41800 | HE55: 0.49 | HF55: Quarter | HG55: Regular Cash | HI55: 41682 | HJ55: 41710 | HK55: 41712 | HL55: 41723 | HM55: 0.28 | HN55: Quarter | HO55: Regular Cash | HQ55: 41716 | HR55: 41731 | HS55: 41733 | HT55: 41759 | HU55: 0.38 | HV55: Quarter | HW55: Regular Cash | HY55: 42034 | HZ55: 42040 | IA55: 42044 | IB55: 42062 | IC55: 5 | ID55: None | IE55: Special Cash | IG55: 41668 | IH55: 41676 | II55: 41680 | IJ55: 41708 | IK55: 0.63 | IL55: Quarter | IM55: Regular Cash
A56: 41627 | B56: 41628 | C56: 41632 | D56: 41670 | E56: 0.98025 | F56: Quarter | G56: Income | I56: 41718 | J56: 41719 | K56: 41723 | L56: 41759 | M56: 0.20606 | N56: Quarter | O56: Income | Q56: 41718 | R56: 41719 | S56: 41723 | T56: 41729 | U56: 0.07866 | V56: Quarter | W56: Income | AG56: 41752 | AH56: 41767 | AI56: 41771 | AJ56: 41774 | AK56: 0.1175 | AL56: Quarter | AM56: Regular Cash | BM56: 41597 | BN56: 41688 | BO56: 41690 | BP56: 41711 | BQ56: 0.28 | BR56: Quarter | BS56: Regular Cash | CC56: 41767 | CD56: 41779 | CE56: 41781 | CF56: 41803 | CG56: 0.002125 | CH56: Quarter | CI56: Regular Cash | DI56: 41703 | DJ56: 41716 | DK56: 41718 | DL56: 41729 | DM56: 0.027 | DN56: Quarter | DO56: Regular Cash | FU56: 41626 | FV56: 41642 | FW56: 41646 | FX56: 41667 | FY56: 0.12 | FZ56: Quarter | GA56: Regular Cash | HA56: 41624 | HB56: 41682 | HC56: 41684 | HD56: 41708 | HE56: 0.49 | HF56: Quarter | HG56: Regular Cash | HI56: 41586 | HJ56: 41612 | HK56: 41614 | HL56: 41625 | HM56: 0.28 | HN56: Quarter | HO56: Regular Cash | HQ56: 41618 | HR56: 41641 | HS56: 41645 | HT56: 41670 | HU56: 0.38 | HV56: Quarter | HW56: Regular Cash | HY56: 41940 | HZ56: 41955 | IA56: 41957 | IB56: 41971 | IC56: 0.355 | ID56: Quarter | IE56: Regular Cash | IG56: 41577 | IH56: 41585 | II56: 41590 | IJ56: 41618 | IK56: 0.63 | IL56: Quarter | IM56: Regular Cash
... A62: 41074 | B62: 41075 | C62: 41079 | D62: 41121 | E62: 0.68826 | F62: Quarter | G62: Income | I62: 41263 | J62: 41264 | K62: 41269 | L62: 41274 | M62: 0.36663 | N62: Quarter | O62: Income | Q62: 41172 | R62: 41173 | S62: 41177 | T62: 41185 | U62: 0.06498 | V62: Quarter | W62: Income | AG62: 41207 | AH62: 41220 | AI62: 41225 | AJ62: 41228 | AK62: 0.094643 | AL62: Quarter | AM62: Regular Cash | BM62: 41073 | BN62: 41135 | BO62: 41137 | BP62: 41165 | BQ62: 0.2 | BR62: Quarter | BS62: Regular Cash | CC62: 41221 | CD62: 41233 | CE62: 41236 | CF62: 41257 | CG62: 0.001875 | CH62: Quarter | CI62: Regular Cash | DI62: 41151 | DJ62: 41170 | DK62: 41172 | DL62: 41183 | DM62: 0.016 | DN62: Quarter | DO62: Regular Cash | FU62: 41172 | FV62: 41192 | FW62: 41194 | FX62: 41215 | FY62: 0.06 | FZ62: Quarter | GA62: Regular Cash | HA62: 41079 | HB62: 41134 | HC62: 41136 | HD62: 41162 | HE62: 0.49 | HF62: Quarter | HG62: Regular Cash | HI62: 41066 | HJ62: 41073 | HK62: 41075 | HL62: 41082 | HM62: 0.2125 | HN62: Quarter | HO62: Regular Cash | HQ62: 41044 | HR62: 41093 | HS62: 41096 | HT62: 41121 | HU62: 0.3 | HV62: Quarter | HW62: Regular Cash | HY62: 41394 | HZ62: 41409 | IA62: 41411 | IB62: 41425 | IC62: 0.31 | ID62: Quarter | IE62: Regular Cash | IG62: 41024 | IH62: 41039 | II62: 41043 | IJ62: 41071 | IK62: 0.57 | IL62: Quarter | IM62: Regular Cash
A63: 40983 | B63: 40984 | C63: 40988 | D63: 41029 | E63: 0.61389 | F63: Quarter | G63: Income | I63: 41172 | J63: 41173 | K63: 41177 | L63: 41213 | M63: 0.2002 | N63: Quarter | O63: Income | Q63: 41074 | R63: 41075 | S63: 41079 | T63: 41087 | U63: 0.054285 | V63: Quarter | W63: Income | AG63: 41114 | AH63: 41130 | AI63: 41134 | AJ63: 41137 | AK63: 0.094643 | AL63: Quarter | AM63: Regular Cash | BM63: 40981 | BN63: 41044 | BO63: 41046 | BP63: 41074 | BQ63: 0.2 | BR63: Quarter | BS63: Regular Cash | DI63: 41067 | DJ63: 41074 | DK63: 41078 | DL63: 41089 | DM63: 0.015 | DN63: Quarter | DO63: Regular Cash | FU63: 41078 | FV63: 41101 | FW63: 41103 | FX63: 41124 | FY63: 0.06 | FZ63: Quarter | GA63: Regular Cash | HA63: 41015 | HB63: 41040 | HC63: 41044 | HD63: 41068 | HE63: 0.49 | HF63: Quarter | HG63: Regular Cash | HI63: 40948 | HJ63: 40969 | HK63: 40973 | HL63: 40987 | HM63: 0.1625 | HN63: Quarter | HO63: Regular Cash | HQ63: 40981 | HR63: 41002 | HS63: 41004 | HT63: 41029 | HU63: 0.3 | HV63: Quarter | HW63: Regular Cash | HY63: 41298 | HZ63: 41311 | IA63: 41313 | IB63: 41327 | IC63: 0.275 | ID63: Quarter | IE63: Regular Cash | IG63: 40933 | IH63: 40947 | II63: 40949 | IJ63: 40977 | IK63: 0.47 | IL63: Quarter | IM63: Regular Cash
A64: 40892 | B64: 40893 | C64: 40897 | D64: 40939 | E64: 0.77013 | F64: Quarter | G64: Income | I64: 41074 | J64: 41075 | K64: 41079 | L64: 41121 | M64: 0.14312 | N64: Quarter | O64: Income | Q64: 40983 | R64: 40984 | S64: 40988 | T64: 40996 | U64: 0.0482 | V64: Quarter | W64: Income | BM64: 40891 | BN64: 40953 | BO64: 40955 | BP64: 40976 | BQ64: 0.2 | BR64: Quarter | BS64: Regular Cash | DI64: 40976 | DJ64: 40983 | DK64: 40987 | DL64: 40998 | DM64: 0.013 | DN64: Quarter | DO64: Regular Cash | FU64: 40988 | FV64: 41008 | FW64: 41010 | FX64: 41031 | FY64: 0.06 | FZ64: Quarter | GA64: Regular Cash | HA64: 40889 | HB64: 40952 | HC64: 40954 | HD64: 40977 | HE64: 0.49 | HF64: Quarter | HG64: Regular Cash | HI64: 40851 | HJ64: 40882 | HK64: 40884 | HL64: 40898 | HM64: 0.1625 | HN64: Quarter | HO64: Regular Cash | HQ64: 40890 | HR64: 40912 | HS64: 40914 | HT64: 40939 | HU64: 0.25 | HV64: Quarter | HW64: Regular Cash | HY64: 41241 | HZ64: 41249 | IA64: 41253 | IB64: 41261 | IC64: 7 | ID64: None | IE64: Special Cash | IG64: 40842 | IH64: 40855 | II64: 40857 | IJ64: 40886 | IK64: 0.47 | IL64: Quarter | IM64: Regular Cash
A65: 40801 | B65: 40802 | C65: 40806 | D65: 40847 | E65: 0.62495 | F65: Quarter | G65: Income | I65: 40983 | J65: 40984 | K65: 40988 | L65: 41029 | M65: 0.11283 | N65: Quarter | O65: Income | Q65: 40892 | R65: 40893 | S65: 40897 | T65: 40905 | U65: 0.054615 | V65: Quarter | W65: Income | BM65: 40806 | BN65: 40862 | BO65: 40864 | BP65: 40885 | BQ65: 0.2 | BR65: Quarter | BS65: Regular Cash | DI65: 40886 | DJ65: 40892 | DK65: 40896 | DL65: 40907 | DM65: 0.012 | DN65: Quarter | DO65: Regular Cash | FU65: 40897 | FV65: 40917 | FW65: 40919 | FX65: 40940 | FY65: 0.06 | FZ65: Quarter | GA65: Regular Cash | HA65: 40833 | HB65: 40857 | HC65: 40862 | HD65: 40886 | HE65: 0.49 | HF65: Quarter | HG65: Regular Cash | HI65: 40758 | HJ65: 40788 | HK65: 40793 | HL65: 40807 | HM65: 0.1625 | HN65: Quarter | HO65: Regular Cash | HQ65: 40806 | HR65: 40820 | HS65: 40822 | HT65: 40847 | HU65: 0.25 | HV65: Quarter | HW65: Regular Cash | HY65: 41212 | HZ65: 41227 | IA65: 41229 | IB65: 41243 | IC65: 0.275 | ID65: Quarter | IE65: Regular Cash | IG65: 40751 | IH65: 40765 | II65: 40767 | IJ65: 40795 | IK65: 0.47 | IL65: Quarter | IM65: Regular Cash
A66: 40710 | B66: 40711 | C66: 40715 | D66: 40753 | E66: 0.62762 | F66: Quarter | G66: Income | I66: 40554 | J66: 40893 | K66: 40897 | L66: 40907 | M66: 0.16052 | N66: Quarter | O66: Income | Q66: 40801 | R66: 40802 | S66: 40806 | T66: 40814 | U66: 0.04675 | V66: Quarter | W66: Income | BM66: 40709 | BN66: 40771 | BO66: 40773 | BP66: 40794 | BQ66: 0.16 | BR66: Quarter | BS66: Regular Cash | DI66: 40794 | DJ66: 40801 | DK66: 40805 | DL66: 40816 | DM66: 0.011 | DN66: Quarter | DO66: Regular Cash | FU66: 40806 | FV66: 40823 | FW66: 40828 | FX66: 40849 | FY66: 0.06 | FZ66: Quarter | GA66: Regular Cash | HA66: 40714 | HB66: 40766 | HC66: 40770 | HD66: 40795 | HE66: 0.49 | HF66: Quarter | HG66: Regular Cash | HI66: 40688 | HJ66: 40697 | HK66: 40701 | HL66: 40715 | HM66: 0.1625 | HN66: Quarter | HO66: Regular Cash | HQ66: 40680 | HR66: 40725 | HS66: 40730 | HT66: 40755 | HU66: 0.25 | HV66: Quarter | HW66: Regular Cash | HY66: 41113 | HZ66: 41129 | IA66: 41131 | IB66: 41145 | IC66: 0.275 | ID66: Quarter | IE66: Regular Cash | IG66: 40660 | IH66: 40674 | II66: 40676 | IJ66: 40704 | IK66: 0.47 | IL66: Quarter | IM66: Regular Cash
A67: 40619 | B67: 40620 | C67: 40624 | D67: 40662 | E67: 0.55332 | F67: Quarter | G67: Income | I67: 40554 | J67: 40802 | K67: 40806 | L67: 40847 | M67: 0.10434 | N67: Quarter | O67: Income | Q67: 40710 | R67: 40711 | S67: 40715 | T67: 40723 | U67: 0.049115 | V67: Quarter | W67: Income | BM67: 40616 | BN67: 40680 | BO67: 40682 | BP67: 40703 | BQ67: 0.16 | BR67: Quarter | BS67: Regular Cash | DI67: 40703 | DJ67: 40709 | DK67: 40711 | DL67: 40724 | DM67: 0.009 | DN67: Quarter | DO67: Regular Cash | FU67: 40716 | FV67: 40735 | FW67: 40737 | FX67: 40758 | FY67: 0.06 | FZ67: Quarter | GA67: Regular Cash | HA67: 40651 | HB67: 40674 | HC67: 40676 | HD67: 40704 | HE67: 0.49 | HF67: Quarter | HG67: Regular Cash | HI67: 40584 | HJ67: 40605 | HK67: 40609 | HL67: 40623 | HM67: 0.125 | HN67: Quarter | HO67: Regular Cash | HQ67: 40620 | HR67: 40637 | HS67: 40639 | HT67: 40663 | HU67: 0.25 | HV67: Quarter | HW67: Regular Cash | HY67: 41038 | HZ67: 41052 | IA67: 41054 | IB67: 41068 | IC67: 0.275 | ID67: Quarter | IE67: Regular Cash | IG67: 40569 | IH67: 40582 | II67: 40584 | IJ67: 40612 | IK67: 0.44 | IL67: Quarter | IM67: Regular Cash
A68: 40528 | B68: 40529 | C68: 40533 | D68: 40574 | E68: 0.65276 | F68: Quarter | G68: Income | I68: 40554 | J68: 40711 | K68: 40715 | L68: 40753 | M68: 0.12079 | N68: Quarter | O68: Income | Q68: 40619 | R68: 40620 | S68: 40624 | T68: 40632 | U68: 0.041795 | V68: Quarter | W68: Income | BM68: 40527 | BN68: 40589 | BO68: 40591 | BP68: 40612 | BQ68: 0.16 | BR68: Quarter | BS68: Regular Cash | DI68: 40612 | DJ68: 40618 | DK68: 40620 | DL68: 40632 | DM68: 0.008 | DN68: Quarter | DO68: Regular Cash | FU68: 40626 | FV68: 40644 | FW68: 40646 | FX68: 40667 | FY68: 0.06 | FZ68: Quarter | GA68: Regular Cash | HA68: 40525 | HB68: 40585 | HC68: 40589 | HD68: 40612 | HE68: 0.49 | HF68: Quarter | HG68: Regular Cash | HI68: 40484 | HJ68: 40515 | HK68: 40519 | HL68: 40533 | HM68: 0.125 | HN68: Quarter | HO68: Regular Cash | HQ68: 40526 | HR68: 40547 | HS68: 40549 | HT68: 40574 | HU68: 0.05 | HV68: Quarter | HW68: Regular Cash | HY68: 40934 | HZ68: 40947 | IA68: 40949 | IB68: 40963 | IC68: 0.24 | ID68: Quarter | IE68: Regular Cash | IG68: 40478 | IH68: 40491 | II68: 40494 | IJ68: 40522 | IK68: 0.44 | IL68: Quarter | IM68: Regular Cash
A69: 40437 | B69: 40438 | C69: 40442 | D69: 40480 | E69: 0.60213 | F69: Quarter | G69: Income | I69: 40554 | J69: 40620 | K69: 40624 | L69: 40662 | M69: 0.07687 | N69: Quarter | O69: Income | Q69: 40528 | R69: 40529 | S69: 40533 | T69: 40541 | U69: 0.045 | V69: Quarter | W69: Income | BM69: 40442 | BN69: 40498 | BO69: 40500 | BP69: 40521 | BQ69: 0.16 | BR69: Quarter | BS69: Regular Cash | DI69: 40514 | DJ69: 40525 | DK69: 40527 | DL69: 40542 | DM69: 0.007 | DN69: Quarter | DO69: Regular Cash | FU69: 40528 | FV69: 40557 | FW69: 40562 | FX69: 40583 | FY69: 0.05 | FZ69: Quarter | GA69: Regular Cash | HA69: 40469 | HB69: 40492 | HC69: 40497 | HD69: 40522 | HE69: 0.49 | HF69: Quarter | HG69: Regular Cash | HI69: 40394 | HJ69: 40431 | HK69: 40435 | HL69: 40449 | HM69: 0.125 | HN69: Quarter | HO69: Regular Cash | HQ69: 40442 | HR69: 40455 | HS69: 40457 | HT69: 40482 | HU69: 0.05 | HV69: Quarter | HW69: Regular Cash | HY69: 40841 | HZ69: 40855 | IA69: 40858 | IB69: 40872 | IC69: 0.24 | ID69: Quarter | IE69: Regular Cash | IG69: 40387 | IH69: 40401 | II69: 40403 | IJ69: 40431 | IK69: 0.44 | IL69: Quarter | IM69: Regular Cash
A70: 40346 | B70: 40347 | C70: 40351 | D70: 40389 | E70: 0.53128 | F70: Quarter | G70: Income | I70: 40193 | J70: 40529 | K70: 40533 | L70: 40543 | M70: 0.10832 | N70: Quarter | O70: Income | Q70: 40437 | R70: 40438 | S70: 40442 | T70: 40450 | U70: 0.04039 | V70: Quarter | W70: Income | BM70: 40345 | BN70: 40407 | BO70: 40409 | BP70: 40430 | BQ70: 0.13 | BR70: Quarter | BS70: Regular Cash | FU70: 40437 | FV70: 40455 | FW70: 40457 | FX70: 40485 | FY70: 0.05 | FZ70: Quarter | GA70: Regular Cash | HA70: 40350 | HB70: 40401 | HC70: 40403 | HD70: 40431 | HE70: 0.49 | HF70: Quarter | HG70: Regular Cash | HI70: 40323 | HJ70: 40332 | HK70: 40336 | HL70: 40350 | HM70: 0.125 | HN70: Quarter | HO70: Regular Cash | HQ70: 40316 | HR70: 40360 | HS70: 40365 | HT70: 40390 | HU70: 0.05 | HV70: Quarter | HW70: Regular Cash | HY70: 40742 | HZ70: 40758 | IA70: 40760 | IB70: 40774 | IC70: 0.24 | ID70: Quarter | IE70: Regular Cash | IG70: 40296 | IH70: 40309 | II70: 40311 | IJ70: 40339 | IK70: 0.44 | IL70: Quarter | IM70: Regular Cash
A71: 40255 | B71: 40256 | C71: 40260 | D71: 40298 | E71: 0.48038 | F71: Quarter | G71: Income | I71: 40193 | J71: 40438 | K71: 40442 | L71: 40480 | M71: 0.11155 | N71: Quarter | O71: Income | Q71: 40346 | R71: 40347 | S71: 40351 | T71: 40359 | U71: 0.039465 | V71: Quarter | W71: Income | BM71: 40245 | BN71: 40316 | BO71: 40318 | BP71: 40339 | BQ71: 0.13 | BR71: Quarter | BS71: Regular Cash | FU71: 40353 | FV71: 40371 | FW71: 40373 | FX71: 40394 | FY71: 0.05 | FZ71: Quarter | GA71: Regular Cash | HA71: 40287 | HB71: 40310 | HC71: 40312 | HD71: 40339 | HE71: 0.49 | HF71: Quarter | HG71: Regular Cash | HI71: 40219 | HJ71: 40269 | HK71: 40274 | HL71: 40288 | HM71: 0.03 | HN71: Annual | HO71: Regular Cash | HQ71: 40253 | HR71: 40269 | HS71: 40274 | HT71: 40298 | HU71: 0.05 | HV71: Quarter | HW71: Regular Cash | HY71: 40659 | HZ71: 40674 | IA71: 40676 | IB71: 40690 | IC71: 0.24 | ID71: Quarter | IE71: Regular Cash | IG71: 40205 | IH71: 40217 | II71: 40219 | IJ71: 40247 | IK71: 0.42 | IL71: Quarter | IM71: Regular Cash
I72: 40193 | J72: 40347 | K72: 40351 | L72: 40389 | M72: 0.0893 | N72: Quarter | O72: Income | Q72: 40255 | R72: 40256 | S72: 40260 | T72: 40268 | U72: 0.03655 | V72: Quarter | W72: Income | BM72: 40156 | BN72: 40225 | BO72: 40227 | BP72: 40248 | BQ72: 0.13 | BR72: Quarter | BS72: Regular Cash | FU72: 40262 | FV72: 40280 | FW72: 40282 | FX72: 40303 | FY72: 0.05 | FZ72: Quarter | GA72: Regular Cash | HA72: 40161 | HB72: 40219 | HC72: 40221 | HD72: 40247 | HE72: 0.49 | HF72: Quarter | HG72: Regular Cash | HQ72: 40155 | HR72: 40182 | HS72: 40184 | HT72: 40209 | HU72: 0.05 | HV72: Quarter | HW72: Regular Cash | HY72: 40570 | HZ72: 40583 | IA72: 40585 | IB72: 40599 | IC72: 0.205 | ID72: Quarter | IE72: Regular Cash
I73: 40193 | J73: 40256 | K73: 40260 | L73: 40298 | M73: 0.05146 | N73: Quarter | O73: Income | FU73: 40165 | FV73: 40192 | FW73: 40197 | FX73: 40218 | FY73: 0.05 | FZ73: Quarter | GA73: Regular Cash | HY73: 40458 | HZ73: 40478 | IA73: 40480 | IB73: 40494 | IC73: 0.205 | ID73: Quarter | IE73: Regular Cash
HY74: 40378 | HZ74: 40394 | IA74: 40396 | IB74: 40410 | IC74: 0.205 | ID74: Quarter | IE74: Regular Cash
HY75: 40290 | HZ75: 40303 | IA75: 40305 | IB75: 40319 | IC75: 0.205 | ID75: Quarter | IE75: Regular Cash
HY76: 40206 | HZ76: 40219 | IA76: 40221 | IB76: 40235 | IC76: 0.18 | ID76: Quarter | IE76: Regular Cash
